Workbook

Sheet exportReport
A1: 最后修改时间 | B1: 创建时间 | C1: 项目编号 | D1: 项目名称 | E1: 扣分原因 | F1: 项目概况 | G1: 隧道情况 | H1: 行业分类 | I1: 产品事业部 | J1: 承揽主办方 | K1: 承揽协办方1 | L1: 项目所在省份 | M1: 投资规模（亿元） | N1: 业主单位 | O1: 设计单位 | P1: 施工单位 | Q1: 设备需求预测（产品类型-数量-预计需求时间） | R1: 预计签约日期 | S1: 预计成交金额（元） | T1: 项目经理 | U1: 项目经理2 | V1: 项目详细阶段 | W1: 跟进具体情况描述 | X1: 下一步工作计划 | Y1: 项目阶段 | Z1: 已完成工作与成效 | AA1: 信息等级 | AB1: 所有人 | AC1: 取消跟进原因 | AD1: 取消跟进说明 | AE1: 创建人 | AF1: 目前状态 | AG1: 最后修改人
A2: 46120 | B2: 2025-09-01 08:32:50 | C2: XM-2025090120213 | D2: 浙江物产DZ622盾构机维修改造项目 | F2: 浙江物产工服DZ622盾构机维修改造，更换主轴承、新制刀盘、二级维修 | G2: 区间长度1205m | H2: 地铁-5 | I2: 掘进机事业部 | J2: 华东区域 | K2: 华南区域 | L2: 浙江 | M2: 5.0000000000 | N2: 浙江物产工程技术服务有限公司 | P2: 浙江物产工程技术服务有限公司 | Q2: ZTE6410-1-(2025-12-20); | R2: 2025-12-10 | S2: CNY 5,900,000.000 | T2: 唐作栋 | W2: 已完成洽谈，合同总价590万，已签订定购函 | X2: 2026年4月完成合同签订 | Y2: 合同评审 | Z2: 已完成洽谈，合同总价590万，已签订定购函 | AA2: 一般信息（Ⅲ级） | AB2: 唐作栋 | AE2: 唐作栋 | AF2: 跟进中 | AG2: 唐作栋
A3: 46114 | B3: 2021-03-22 16:17:32 | C3: XM-202103225487 | D3: 浙江金华金武永东轨道交通项目 | F3: 金武永东市域铁路预计总投资435.2亿元，线路全长111.7公里，其中地下线长约32.9公里，占比29.5%，位于金华市、武义县、永康市的中心城区和在建横店机场、横店镇；高架线及过渡段长约72.4公里，山岭隧道线长约6.4公里。全线设站26座，其中地下站14座，高架站12座。换乘站4座，平均站间距约4.5公里。 | G3: 地下线长约32.9公里 | H3: 地铁-5 | I3: 掘进机事业部 | J3: 华东区域 | K3: 华东区域 | L3: 浙江 | M3: 435.2000000000 | N3: 金华市轨道交通集团有限公司 | O3: 北京城建院 | Q3: 土压平衡盾构机-4-(/); | R3: 2027-10-30 | S3: CNY 40,000,000.000 | T3: 万赛 | U3: 万赛 | V3: 定测及初步设计阶段 | W3: 目前业主及设计单位正在准备报批工作 | X3: 持续跟进项目进展情况 | Y3: 定测及初步设计阶段 | Z3: 1、核心问题：目前项目项目还未获批； 2、工作思路：等项目获批后，与设计院及业主、施工单位开展拜访、技术交流等工作； 3、关键点：跟踪项目审批、招标等时间节点，确定设备需求型号； 4、行动计划：时刻保持与客户的联系，配合各施工单位投标工作。 | AA3: 重点信息（Ⅱ级） | AB3: 唐作栋 | AE3: 接口专用帐号 | AF3: 跟进中 | AG3: 万赛
A4: 46113 | B4: 2024-12-31 10:27:46 | C4: XM-2024123118565 | D4: 义龙庆高速公路义乌至龙泉段（金华段）▲ | F4: 全长约105.5公里，采用双向四/六车道高速公路标准，设计速度120km/h | G4: 桥隧比83% | H4: 公路-4 | I4: 特种装备事业部 | J4: 华东区域 | L4: 浙江 | M4: 372.2000000000 | N4: 浙江金华义龙庆高速公路有限公司 | R4: 2026-04-30 | S4: CNY 8,000,000.000 | T4: 万赛 | V4: 设备招标阶段 | W4: 施工已中标，一共九个标段，1公里以上的隧道要求上全电脑三臂凿岩台车，落实目前2标、3标、7标、9标有全电脑三臂凿岩台车需求，按照标书文件要求4个标段分别需要4台设备，合计16台；3标重新招标后，中标单位11月已公示，为浙江交工宏途，正式施工合同近期会完成签订。1月份跟踪各标段情况如下：9标劳务已经确定，设备需求第一台设备计划进展时间是2026年4月1日，目前正在和劳务老板洽谈中；2标、3标、7标目前劳务队还没有确定，预计年后才能完成招标，设备需求等劳务队确认后才能订设备。 | X4: 完成与2标、3标等各标段项目部及施工单位技术交流，劳务老板对接，设备需求时间确认等工作。 | Y4: 项目施工中标公示 | Z4: 9月份已完成与浙高建领导的拜访及交流，同时义龙庆汪副指挥长一同参会，计划国庆节后浙高建领导会组织去我司考察；12月份邀请指挥部及各大机施工项目经理到我司考察交流。 | AA4: 重点信息（Ⅱ级） | AB4: 万赛 | AE4: 万赛 | AF4: 跟进中 | AG4: 万赛
A5: 46113 | B5: 2022-03-30 11:56:51 | C5: XM-2022033010131 | D5: 杭州下沙至嘉兴长安城际铁路 | F5: 本项目线路总体由南向北,由杭州地铁1号线文海南路站引出，自浙江钱塘区下沙街道经海宁高新区至长安镇区，终点杭海城际铁路长安站。项目线路全长约20公里，暂定设车站7座（另预留1座），包含地上、地下车站，最高运行速度120km/h，隨道长度5.10公里，2区间 | G5: 隨道长度5.10公里，2区间 | H5: 轨道交通 | I5: 掘进机研发运营中心 | J5: 华东区域 | L5: 浙江 | M5: 96.8500000000 | N5: 海宁市轨道交通投资建设有限公司 | Q5: 土压平衡盾构机-4-(/); | R5: 2026-06-30 | S5: CNY 15,000,000.000 | T5: 唐作栋 | W5: 剩余1个地下段SG-2标暂未招标，目前已有消息项目内定给中铁十八局市政公司 | X5: 1.与十八局了解相关情况 2.配合系统内单位进行地下段投标 | Y5: 施工图设计阶段 | Z5: 剩余1个地下段SG-2标暂未招标，目前已有消息项目内定给中铁十八局市政公司 | AA5: 重点信息（Ⅱ级） | AB5: 唐作栋 | AE5: 唐作栋 | AF5: 跟进中 | AG5: 唐作栋
A6: 46113 | B6: 2021-03-22 16:17:29 | C6: XM-202103225470 | D6: 文一西路西延工程（三期） | F6: 项目西起临余桥东，与现状已建科技大道（临安段）衔接，东至南湖圩堤北6#盾构井，全长约5公里。项目分为快速路系统和地面辅道系统两部分。快速路系统重，地下快速路长约1.77公里，地面快速路长约3.25公里；地面辅道全长约3.76公里。 | G6: 其中地下快速路采用盾构法，长约1.77km，含1.24km 盾构隧道和0.53km 明挖隧道 | H6: 城建 | I6: 掘进机研发运营中心 | J6: 华东区域 | K6: 无部门 | L6: 浙江 | M6: 93.0000000000 | N6: 杭州余杭城市发展投资集团有限公司 | O6: 中国电建集团华东勘测设计研究院有限公司 | Q6: 泥水平衡盾构机-1-(2027-02-01); | R6: 2026-12-31 | S6: CNY 50,000,000.000 | T6: 唐作栋 | U6: 刘新峥 | V6: 定测及初步设计阶段 | W6: 1.中交隧道局中标施工标，我司无可租赁设备 2.中铁十五局横琴项目设备目前闲置，正在对接进行转租或进行维修改造 | X6: 跟进中交隧道局，了解设备需求情况 | Y6: 项目施工中标公示 | Z6: 1.中交隧道局中标施工标，我司无可租赁设备 2.中铁十五局横琴项目设备目前闲置，正在对接进行转租或进行维修改造 | AA6: 重点信息（Ⅱ级） | AB6: 唐作栋 | AE6: 接口专用帐号 | AF6: 跟进中 | AG6: 唐作栋
A7: 46113 | B7: 2024-03-17 00:00:10 | C7: XM-2024031716419 | D7: 杭州站经望江门越江隧道至杭州南站连接线工程 | F7: 望江门隧道是杭州铁路枢纽规划中预留的一条过江通道。北端连接杭州城站，以过江隧道的形式穿过钱塘江，进入滨江区境内，继续以地下隧道的形式向东延伸，经过萧山城区。最终向东可连接机场高铁，连通萧山机场，向南可连至火车南站。线路全长14.74km，其中地下隧道长11.7km,计划2024启动可研编制 | G7: 地下隧道长11.7km | H7: 铁路-2 | I7: 掘进机事业部 | J7: 华东区域 | L7: 浙江 | M7: 100.0000000000 | N7: 杭州铁路枢纽工程建设指挥部 | O7: 中铁第四勘察设计院集团有限公司 | Q7: ZTS13200-3-(2026-12-31); | R7: 2026-12-31 | S7: CNY 100,000,000.000 | T7: 唐作栋 | W7: 铁四院中标望江门隧道建设方案研究，已对接铁四院杭州分院了解相关情况，暂定隧道管片外径12m8 | X7: 1.持续跟进铁四院，了解项目进展 2.4月拜访杭州铁路建设枢纽指挥部，进行大直径盾构技术交流 | Y7: 定测及初步设计阶段 | Z7: 铁四院中标望江门隧道建设方案研究，已对接铁四院杭州分院了解相关情况，暂定隧道管片外径12m8 | AA7: 重点信息（Ⅱ级） | AB7: 唐作栋 | AE7: 唐作栋 | AF7: 跟进中 | AG7: 唐作栋
A8: 46113 | B8: 2024-04-01 17:44:56 | C8: XM-2024040116522 | D8: G2531杭州至上饶高速公路（杭淳开高速公路）（杭州段） | F8: 杭州至上饶高速公路中环至浙赣界（杭淳开高速公路）项目工可推荐方案起点位于富阳区银湖街道六家山村附近与杭州中环相交，起点桩号K0+000，浙江段止于浙江省开化县与江西省德兴市交界处，终点桩号K246+057，路线全长约246km（含千黄高速公路利用段约20km），新建里程约226km。工程总投资约709亿元 | G8: 隧道总长度约76km | H8: 公路-4 | I8: 特种装备事业部 | J8: 华东区域 | L8: 浙江 | M8: 709.0000000000 | N8: 浙江省交通投资集团有限公司 | O8: 浙江数智交院科技股份有限公司 | Q8: ZYS113-4-(2025-06-30); | R8: 2026-03-31 | S8: CNY 30,000,000.000 | T8: 唐作栋 | U8: 刘新峥 | W8: 3月拜访杭淳开高速杭州段建设指挥部及2、3、7、8、10、12标项目部，了解建设指挥部对大机施工设备的要求，桐庐-富阳段3月26日给各项目部宣贯设备要求，淳安段2月底已向各项目部下发设备要求通知。目前各项目部正在与劳务分包签订合同，设备均由劳务队自带。 | X8: 1.从建设指挥部切入，在3km以上长大隧道，推行全电脑三臂凿岩台车 2.与各项目部及分包老板进行设备采购洽谈 | Y8: 施工图设计阶段 | Z8: 3月拜访杭淳开高速杭州段建设指挥部及2、3、7、8、10、12标项目部，了解建设指挥部对大机施工设备的要求，桐庐-富阳段3月26日给各项目部宣贯设备要求，淳安段2月底已向各项目部下发设备要求通知。目前各项目部正在与劳务分包签订合同，设备均由劳务队自带。 | AA8: 重点信息（Ⅱ级） | AB8: 唐作栋 | AE8: 唐作栋 | AF8: 跟进中 | AG8: 唐作栋
A9: 46112 | B9: 2021-03-22 16:17:29 | C9: XM-202103225471 | D9: 漳汕铁路项目 | F9: 1标中铁十一局一公司，门口山隧道5800m 2标中铁十二局二公司，大岭隧道13434m；3标中铁四局五公司，林萍隧道2800m； 4标中铁大桥局六公司，凤山岭隧道1870m。 | G9: / | H9: 铁路 | I9: 特种装备事业部 | J9: 华东区域 | K9: 无部门 | L9: 福建 | M9: 210.0000000000 | N9: 东南沿海铁路福建公司 | O9: 铁二院 | P9: 待定 | R9: 2026-06-30 | S9: CNY 14,000,000.000 | T9: 杨志胜 | V9: 定测及初步设计阶段 | W9: 因施工单价原因，浙江万慧詹总还未确定是否使用大机施工，需求待定。 | X9: 配合经销商继续保持跟进。 | Y9: 商务交流 | Z9: 因施工单价原因，浙江万慧詹总还未确定是否使用大机施工，需求待定。 | AA9: 重点信息（Ⅱ级） | AB9: 杨志胜 | AE9: 接口专用帐号 | AF9: 跟进中 | AG9: 杨志胜
A10: 46112 | B10: 2023-06-04 14:11:20 | C10: XM-2023060413963 | D10: 铅山抽水蓄能项目 | F10: 铅山县高桥抽水蓄能电站位于铅山县境内，电站拟建规模为200～240万千瓦。项目动态投资约200亿元 | G10: 引水洞、交通洞，通风安全洞等 | H10: 水利水电-0 | I10: 掘进机事业部 | J10: 华东区域 | L10: 江西 | M10: 200.0000000000 | N10: 中广核风电有限公司 | O10: 中国电建华东勘测设计院 | P10: 待定 | Q10: 掘进机-1-(/); | R10: 2026-09-30 | S10: CNY 0.000 | T10: 杨志胜 | W10: 本项目原投资主体已退出，11月3日已发布了投资主体优选公告，计划12月底前确定新的投资主体。本项目原投资主体国电投已退出，新的投资人已确定为中广核风电有限公司，项目后续进展待跟进。 | X10: 计划对接中广核风电公司项目负责人。 | Y10: 定测及初步设计阶段 | Z10: 本项目原投资主体已退出，11月3日已发布了投资主体优选公告，计划12月底前确定新的投资主体。本项目原投资主体国电投已退出，新的投资人已确定为中广核风电有限公司，项目后续进展待跟进。 | AA10: 一般信息（Ⅲ级） | AB10: 杨志胜 | AE10: 郭亚楠 | AF10: 跟进中 | AG10: 杨志胜
A11: 46112 | B11: 2023-06-04 15:23:57 | C11: XM-2023060413977 | D11: 遂川抽水蓄能电站 | F11: 进厂交通洞1786m，断面8*8.8，通风安全洞1087m，断面7*6.5，施工支洞共3782m. | G11: 进厂交通洞1786m，断面8*8.8，通风安全洞1087m，断面7*6.5，施工支洞共3782m. | H11: 水利水电-0 | I11: 特种装备事业部 | J11: 华东区域 | L11: 江西 | M11: 110.0000000000 | N11: 江西省投资集团 | O11: 中国电建华东勘测设计院 | P11: 待定 | R11: 2026-09-30 | S11: CNY 0.000 | T11: 杨志胜 | W11: 本项目原投资主体已退出，11月3日已发布了投资主体优选公告，计划12月底前确定新的投资主体。新的投资人确定为江西省投资集团，已拜访江西省投资集团下属峰山抽水蓄能公司朱胜江总和王志刚总，项目预计年底前招先期标。 | X11: 拜访江西省投资集团下属峰山抽蓄公司领导，跟进项目推进计划，开展相关技术交流。 | Y11: 定测及初步设计阶段 | Z11: 已拜访江西省投资集团下属峰山抽水蓄能公司朱胜江总和王志刚总，项目预计年底前招先期标。 | AA11: 一般信息（Ⅲ级） | AB11: 杨志胜 | AE11: 郭亚楠 | AF11: 跟进中 | AG11: 杨志胜
A12: 46112 | B12: 2023-06-04 15:25:58 | C12: XM-2023060413982 | D12: 永新抽水蓄能电站 | F12: 进厂交通洞1485m，断面尺寸8*8.5，通风安全洞1138m，断面尺寸7*6.5，采用钻爆法全断面开挖。自流排水洞4011m,断面3*3，拟采用TBM施工。 | G12: 进厂交通洞1485m，断面尺寸8*8.5，通风安全洞1138m，断面尺寸7*6.5，采用钻爆法全断面开挖。自流排水洞4011m,断面3*3，拟采用TBM施工。 | H12: 水利水电-0 | I12: 掘进机事业部 | J12: 华东区域 | L12: 江西 | M12: 80.0000000000 | N12: 华能（永新）抽水蓄能有限责任公司 | O12: 中国电建华东勘测设计院 | P12: 安能二局 | R12: 2026-06-30 | S12: CNY 0.000 | T12: 杨志胜 | W12: 已对接安能二局市场部杨邑文，安能二局中标筹建期进厂交通洞兼通风安全洞工程，TBM标段暂未招标。本月无最新进展。 | X12: 近期计划拜访永新抽蓄公司范庆龙总，交流钻爆法及盾构机施工。 | Y12: 定测及初步设计阶段 | Z12: 已对接安能二局市场部杨邑文，安能二局中标筹建期进厂交通洞兼通风安全洞工程，TBM标段暂未招标。本月无最新进展。 | AA12: 一般信息（Ⅲ级） | AB12: 杨志胜 | AE12: 郭亚楠 | AF12: 跟进中 | AG12: 杨志胜
A13: 46112 | B13: 2023-06-04 15:28:00 | C13: XM-2023060413978 | D13: 永丰抽水蓄能电站 | F13: 电站总装机容量1200MW（4×300MW）为一等大（1）型工程。枢纽工程主要建筑物由上水库、下水库、输水系统、地下厂房和开关站等组成。 | G13: / | H13: 水利水电-0 | I13: 特种装备事业部 | J13: 华东区域 | L13: 江西 | M13: 80.0000000000 | N13: 江西华电抽水蓄能有限公司 | O13: 中国电建集团华东勘测设计研究院有限公司 | P13: 待定 | R13: 2026-12-31 | S13: CNY 0.000 | T13: 杨志胜 | W13: 2025年3月，水电水利规划设计总院主持评审，预可研通过，同意1200兆瓦方案。现处于可研阶段。暂无明确推进计划。 | X13: 1、对接华东院，了解项目概况及关键信息。 2、对接股份赣南中心，了解系统内单位跟进情况。 | Y13: 项目立项阶段（预可研，初测及可研，环评） | Z13: 已通过铁建赣南经营中心了解项目进展，属于中远期项目，保持关注。 | AA13: 一般信息（Ⅲ级） | AB13: 杨志胜 | AE13: 郭亚楠 | AF13: 跟进中 | AG13: 杨志胜
A14: 46112 | B14: 2024-04-29 14:12:35 | C14: XM-2024042916696 | D14: 厦门钨业武宁县大湖塘北区钨矿20000t/d采选工程 | F14: 现有生产系统为地下开采，平硐开拓，留矿法采矿。本次矿山建设开采方式为露天开采。建设规模：采选矿规模为20000t/d。 | G14: / | H14: 非煤矿山-11 | I14: 矿山装备事业部 | J14: 华东区域 | L14: 江西 | M14: 50.0000000000 | N14: 厦门钨业（江西巨通实业） | O14: 中国瑞林 | P14: 待定 | Q14: 廊道皮带机-1-(/); | R14: 2026-12-31 | S14: CNY 0.000 | T14: 杨志胜 | W14: 因矿区发现了稀土储量，该项目暂时停滞，后续推进计划暂不明确。该项目重新纳入了江西省2026年预备开工项目。 | X14: 计划近期拜访中国瑞林门总，了解项目最新进展，适时开展技术交流。 | Y14: 项目立项阶段（预可研，初测及可研，环评） | Z14: 前期拜访了中国瑞林矿山事业部门总，因矿区发现了稀土储量，该项目暂时停滞，后续推进计划暂不明确。现该项目重新纳入了江西省2026年预备开工项目。 | AA14: 一般信息（Ⅲ级） | AB14: 杨志胜 | AE14: 郭亚楠 | AF14: 跟进中 | AG14: 杨志胜
A15: 46112 | B15: 2025-05-30 22:27:47 | C15: XM-2025053019572 | D15: 市域供水联通保障工程（九溪水厂过江通道） | F15: 本项目投资估算 37733.75万元，建设规模 ：本项目建设内容为（1）滨江区与西湖区实现互联互通新建管线，主要为新建供水管道DN1600mm长度约3.2公里，新建供水管DN1200mm长度约1.1公里；（2）新建过江盾构管廊一座内径5.5m，外径6.2m，长度约为1.8公里 。 | G15: 新建过江盾构管廊一座，内径5.5m，外径6.2m， 长度约为1.8公里 | H15: 市政管廊-6 | I15: 掘进机事业部 | J15: 华东区域 | L15: 浙江 | M15: 3.7700000000 | N15: 杭州滨江水务有限公司 | O15: 中国电建集团华东勘测设计研究院有限公司 | P15: 中建三局集团有限公司 | Q15: ZTS6410-1-(2026-12-31); | R15: 2026-12-31 | S15: CNY 9,000,000.000 | T15: 唐作栋 | W15: 中建三局中标施工标，正在对接中建三局了解设备需求情况 | X15: 跟进了解是否有可用设备 | Y15: 项目施工中标公示 | Z15: 中建三局中标施工标，正在对接中建三局了解设备需求情况 | AA15: 一般信息（Ⅲ级） | AB15: 唐作栋 | AE15: 唐作栋 | AF15: 跟进中 | AG15: 唐作栋
A16: 46112 | B16: 2025-03-31 10:42:11 | C16: XM-2025033119073 | D16: 赣州市中心城区供水一体化项目取水及隧洞建设工程（上犹江水资源配置工程） | F16: 骨干引调水线路总长108.6km，其中引水隧洞27.0km、城乡供水输水管道长63.1km、灌溉输水干管长18.5km。引水隧洞拟采用TBM施工。 | G16: 引水隧洞27.0km，采用TBM施工，开挖直径5米。 | H16: 市政管廊-6 | I16: 掘进机事业部 | J16: 华东区域 | L16: 江西 | M16: 58.0000000000 | N16: 赣州市市政公用集团 | O16: 上海市政院 | Q16: ZTT5260-2-(/);ZTE5260-2-(/); | R16: 2026-09-30 | S16: CNY 100,000,000.000 | T16: 杨志胜 | W16: 引水隧洞27公里，采用TBM施工，开挖直径5米。项目业主单位调整为赣州市市政公用集团，计划2026年6月份启动招标，系统内11局、18局、14局均在跟进。已对接赣州市水务集团和上海市政院，并为设计院提供了TBM和盾构机选型建议及专家。 | X16: 1、协同18局隧道公司对接业主单位赣州市水务集团； 2、拜访上海市政院，交流TBM施工。 3、参加业主和设计院组织的设备选型专家评审会。 | Y16: 项目立项阶段（预可研，初测及可研，环评） | Z16: 已对接赣州市水务集团和上海市政院，并为设计院提供了TBM和盾构机选型建议及专家。 | AA16: 重点信息（Ⅱ级） | AB16: 杨志胜 | AE16: 杨志胜 | AF16: 跟进中 | AG16: 杨志胜
A17: 46112 | B17: 2024-12-30 19:58:12 | C17: XM-2024123018582 | D17: 浙江特高压交流环网嘉兴-宁波段跨越钱塘江输电工程GIL管廊 | F17: 项目处于可研阶段，管廊长度约4.9km，采用11m6管片外径泥水平衡盾构机施工 | G17: 隧道长度约4.9km，采用11m6管片外径泥水平衡盾构机施工 | H17: 电力-14 | I17: 掘进机事业部 | J17: 华东区域 | L17: 浙江 | M17: 100.0000000000 | N17: 国网浙江省电力有限公司 | O17: 中国电力工程顾问集团华东电力设计院有限公司 | Q17: ZTS12000-1-(/); | R17: 2026-12-31 | S17: CNY 100,000,000.000 | T17: 唐作栋 | W17: 1.中铁十四局大盾构公司已中标施工标，投标时为保证业绩分，使用海瑞克技术方案投标。 2.已拜访业主单位，业主暂未强制要求使用进口设备或投标厂商设备，国网特高压事业部拟考察国产设备厂商设备。 | X17: 1.与十四局进行对接洽谈，了解十四局拟使用设备情况 2.邀请业主前往我司进行考察 | Y17: 项目施工中标公示 | Z17: 1.中铁十四局大盾构公司已中标施工标，投标时为保证业绩分，使用海瑞克技术方案投标。 2.已拜访业主单位，业主暂未强制要求使用进口设备或投标厂商设备，国网特高压事业部拟考察国产设备厂商设备。 | AA17: 重点信息（Ⅱ级） | AB17: 唐作栋 | AE17: 唐作栋 | AF17: 跟进中 | AG17: 唐作栋
A18: 46112 | B18: 2025-04-27 17:35:04 | C18: XM-2025042719283 | D18: 上饶市广丰区壶峤砂岩矿绿色开发运营一体化项目 | F18: 规划建设生产规模不低于600万吨/年，建设期1年，合作期20年，由中铁十九局和上饶市泽海建材有限公司联合中标，十九局中标金额76.84亿元，由广州公司实施。 | G18: 略 | H18: 非煤矿山-11 | I18: 矿山装备事业部 | J18: 华东区域 | L18: 江西 | M18: 89.0000000000 | N18: 上饶市建广绿色建筑材料有限公司 | P18: 中铁十九局广州公司 | Q18: DG600-YS-1-(/); | R18: 2026-09-30 | S18: CNY 30,000,000.000 | T18: 杨志胜 | W18: 该项目具体由十九局广州公司实施，已拜访了十九局江西经营部贾总和项目经理张洋，计划由联合体成员方上饶市泽海建材负责销售及设备采购。 | X18: 计划近期前往现场拜访项目经理张洋，让其引荐合作方泽海建材，交流设备需求。 | Y18: 商务交流 | Z18: 该项目具体由十九局广州公司实施，已拜访了十九局江西经营部贾总和项目经理张洋，计划由联合体成员方上饶市泽海建材负责销售及设备采购。 | AA18: 一般信息（Ⅲ级） | AB18: 杨志胜 | AE18: 杨志胜 | AF18: 跟进中 | AG18: 杨志胜
A19: 46112 | B19: 2024-12-30 20:10:19 | C19: XM-2024123018564 | D19: 沪昆铁路立交(滨江区段)城市枢纽综合管网工程(江南大道 -信诚路)标段 | F19: 南环路综合管廊(东信大道-信诚路)综合管廊工程，路径总长约2.49km，设计外径8.8m | G19: 路径总长约2.49km，设计外径8.8m | H19: 市政管廊-6 | I19: 掘进机事业部 | J19: 华东区域 | L19: 浙江 | M19: 31.2000000000 | N19: 杭州滨江环境发展有限公司 | O19: 中国电建集团华东勘测设计研究院有限公司 | P19: 中国电建集团华东勘测设计研究院有限公司 | Q19: ZTE9100-1-(/); | R19: 2026-12-31 | S19: CNY 22,780,000.000 | T19: 唐作栋 | W19: 业主在2025年已上报项目财政计划并已获得批复，2026年年度投资已落实，年度任务已完成，因此对于项目招标及进度并不是很着急，项目招标时间可能延后至春节后 | X19: 4月30日前拜访中铁十八局、十六局杭州经营部了解项目跟进情况及后续计划安排 | Y19: 项目施工招标阶段 | Z19: 业主在2025年已上报项目财政计划并已获得批复，2026年年度投资已落实，年度任务已完成，因此对于项目招标及进度并不是很着急，项目招标时间可能延后至春节后 | AA19: 一般信息（Ⅲ级） | AB19: 唐作栋 | AE19: 唐作栋 | AF19: 跟进中 | AG19: 唐作栋
A20: 46112 | B20: 2025-06-28 14:14:37 | C20: XM-2025062819740 | D20: 江西漂塘钨业液压掘进台车采购需求 | F20: 江钨集团漂塘钨业计划采购1台液压掘进台车。 | G20: 略 | H20: 非煤矿山-11 | I20: 特种装备事业部 | J20: 华东区域 | L20: 江西 | M20: 10.0000000000 | N20: 江西漂塘钨业有限公司 | Q20: CYDJ45(D)-1-(/); | R20: 2025-12-31 | S20: CNY 1,190,000.000 | T20: 杨志胜 | W20: 我司提供了方案报价，但设备无法满足现场工况要求，最终客户选择采购五新装备的设备，采购价114万。 | X20: 无下一步计划。 | Y20: 设备未中标 | Z20: 供销公司已完成供应商准入的审查，我司已进入合格供应商名录。同时提供了设备技术方案及报价。 | AA20: 一般信息（Ⅲ级） | AB20: 杨志胜 | AE20: 杨志胜 | AF20: 跟进中 | AG20: 杨志胜
A21: 46112 | B21: 2025-05-30 22:36:59 | C21: XM-2025053019573 | D21: 舟山市百兆瓦潮流能发电机组并网示范项目 | F21: 舟山市百兆瓦潮流能发电机组并网示范项目，开展发电机组关键部件的制造工艺技术研究，本项目的大型结构件主要包括塔筒、基座、艇舱及端盖、总成平台等，其特点是大尺寸（单件超过30米）、大重量（单件超过100吨），全焊透Ⅰ级焊缝，并且要求热处理消除焊接应力 | G21: 无 | H21: 水利水电-0 | I21: 特种装备事业部 | J21: 华东区域 | L21: 浙江 | M21: 25.0000000000 | N21: 中铁建发展集团有限公司 | O21: 中铁第四勘察设计院集团有限公司 | Q21: 总成平台基座-40-(/); | R21: 2026-06-30 | S21: CNY 300,000,000.000 | T21: 唐作栋 | W21: 1.戴董事长拟前往发展集团考察调研，由发展集团做本项目的专项汇报后进行下一步推进，但由于时间问题，董事长暂未前往考察 2.林东新能源还在与国家能源局就并网补贴进行洽谈，目前洽谈价格为1.6元 3.暂无最新进展 | X21: 股份公司决策存在阻力，发展集团还在争取获得股份公司批准 跟进了解相关进展 | Y21: 项目立项阶段（预可研，初测及可研，环评） | Z21: 1.已完成股份公司专家评审会 | AA21: 重点信息（Ⅱ级） | AB21: 唐作栋 | AE21: 唐作栋 | AF21: 跟进中 | AG21: 唐作栋
A22: 46112 | B22: 2025-07-30 21:51:39 | C22: XM-2025073019964 | D22: 合肥至温州高速公路浙皖界至桐庐段（湖州北段） | F22: 项目起点位于湖州市长兴县泗安镇小界碑村西北侧浙皖交界处，终于与规划德安高速公路安吉昌硕至天荒坪段交叉处，合计约37.915km。全线共设置桥梁约15904m/42座，隧道约2277m/5座，全线桥隧占比约48.0%。沿线共设置枢纽式互通立体交叉1处，一般式互通立体交叉5处，服务区1处（与互通合建） | G22: 隧道约2277m/5座 | H22: 公路-4 | I22: 特种装备事业部 | J22: 华东区域 | L22: 浙江 | M22: 50.0000000000 | N22: 湖州市公路与运输管理中心 | Q22: HZS180-4-(/); | R22: 2026-12-31 | S22: CNY 8,000,000.000 | T22: 唐作栋 | W22: 初步设计项目，暂无最新进展 | X22: 4月30日前，前往数智交院进行交流，整体对初步设计项目进行了解 | Y22: 项目立项阶段（预可研，初测及可研，环评） | Z22: 初步设计项目，已拜访数智交院了解项目情况 | AA22: 一般信息（Ⅲ级） | AB22: 唐作栋 | AE22: 唐作栋 | AF22: 跟进中 | AG22: 唐作栋
A23: 46112 | B23: 2025-07-30 21:54:11 | C23: XM-2025073019965 | D23: 德清至安吉高速公路德清舞阳至安吉昌硕段 | F23: 项目推荐方案全长24.13公里，全线采用高速公路标准、双向六车道，设计速度100公里/小时。全线设枢纽互通立交2处，一般互通立交2处。共布设桥梁8208.79米/17座(含枢纽互通区及分离主线桥)，其中特大桥3293.79米/2座，大桥4465.00米/10座、中桥450.00米/5座；隧道6座，折合双洞全长11815.00米，其中:特长隧道3826.50米/1座，长隧道6835.00米/3座，中隧道870.00米/1座，短隧道283.50米/1座；全线桥隧占比82.97%。沿线设施包括互通收费站2处，路段监控通信分中心1处，桥隧监控通信站1处。 | G23: 隧道6座，折合双洞全长11815.00米 | H23: 公路-4 | I23: 特种装备事业部 | J23: 华东区域 | L23: 浙江 | M23: 80.0000000000 | N23: 安吉德安高速公路有限公司 | O23: 浙江数智交院科技股份有限公司安吉德安高速公路有限公司 | Q23: ZYS113-1-(/); | R23: 2026-12-31 | S23: CNY 8,000,000.000 | T23: 唐作栋 | W23: 项目正在中标公示中，TJ01标：浙江交工集团股份有限公司，TJ02标：中交一公局集团有限公司 | X23: 跟进中标项目单位，了解设备需求情况。 | Y23: 项目施工中标公示 | Z23: 项目正在中标公示中，TJ01标：浙江交工集团股份有限公司，TJ02标：中交一公局集团有限公司 | AA23: 一般信息（Ⅲ级） | AB23: 唐作栋 | AE23: 唐作栋 | AF23: 跟进中 | AG23: 唐作栋
A24: 46112 | B24: 2025-07-30 21:57:25 | C24: XM-2025073019966 | D24: 德清至安吉高速公路德清雷甸至舞阳段 | F24: 本项目推荐方案全长21.7公里，全线设枢纽互通立交2处，一般互通立交3处（含续建的上柏互通），设德清南互通连接线2.08km/1条，采用一级公路标准，设计速度80km/h，双向四车道，路基宽度25.5米。共布设桥梁12座，全长17832.18米（其中连续高架桥长约16.195km）；全线桥梁占比82.17%。沿线设施包括互通收费站2处，管理分中心1处，服务区1处。项目估算总投资约116.9亿元（其中涉铁费用约9亿元），建安费约57.68亿元（不含涉铁段）。 | G24: / | H24: 公路-4 | I24: 特种装备事业部 | J24: 华东区域 | L24: 浙江 | M24: 116.9000000000 | N24: 湖州市公路与运输管理中心 | Q24: HZS180K-2-(/); | R24: 2026-12-31 | S24: CNY 500.000 | T24: 唐作栋 | W24: 已拜访数智交院，项目处于前期设计阶段 | X24: 4月30日前，拜访数智交院项目设计，了解项目进展 | Y24: 项目立项阶段（预可研，初测及可研，环评） | Z24: 已拜访数智交院，项目处于前期设计阶段 | AA24: 一般信息（Ⅲ级） | AB24: 唐作栋 | AE24: 唐作栋 | AF24: 跟进中 | AG24: 唐作栋
A25: 46112 | B25: 2025-07-30 22:00:05 | C25: XM-2025073019967 | D25: S304临平至安吉公路德清县雷甸至舞阳段 | F25: 路线全长约21.3km。涉铁范围总长1290米，其中宁杭高铁、合杭高铁段690米，宣杭铁路段600米。项目拟采用双向六车道和四车道一级公路标准（兼顾城市道路功能），设计速度采用80km/h，整体式路基宽度39m、41m、47m和33.5m。桥梁总长6202.5m/16座，其中特大桥3717.5m/3座，大桥2005m/7座，项目估算总投资约30.3亿元（其中涉铁费用约4亿元），建安费约18.74亿元（不含涉铁段）。 | G25: / | H25: 公路-4 | I25: 特种装备事业部 | J25: 华东区域 | L25: 浙江 | M25: 34.0000000000 | N25: 湖州市公路与运输管理中心 | O25: 浙江数智交院科技股份有限公司 | Q25: HZS180-2-(/); | R25: 2026-12-31 | S25: CNY 5,000,000.000 | T25: 唐作栋 | W25: 已拜访数智交院，项目处于前期设计阶段，无进展 | X25: 4月30日前，拜访数智交院项目设计，了解项目进展 | Y25: 项目立项阶段（预可研，初测及可研，环评） | Z25: 1.已拜访数智交院，项目处于前期设计阶段，无进展 | AA25: 一般信息（Ⅲ级） | AB25: 唐作栋 | AE25: 唐作栋 | AF25: 跟进中 | AG25: 唐作栋
A26: 46112 | B26: 2025-08-31 18:42:24 | C26: XM-2025083120210 | D26: 文二西路提升改造工程 | F26: 项目西起运溪路，东至荆长大道，长约6.7km，工程内容包括新建下穿隧道、地面道路改造、景观品质提升等。新建文二西路隧道长约2.65km，隧道规模为双向四车道。 | G26: 新建文二西路隧道长约2.65km，隧道规模为双向四车道。 | H26: 城建-1 | I26: 掘进机事业部 | J26: 华东区域 | L26: 浙江 | M26: 25.0000000000 | N26: 杭州余杭城市发展投资集团有限公司 | O26: 中交第二公路勘察设计研究院有限公司 | Q26: ZTS11700-1-(/); | R26: 2026-12-31 | S26: CNY 100,000,000.000 | T26: 唐作栋 | W26: 项目已发布招标计划，计划4月底进行施工招标 | X26: 4月15日前拜访业主及各施工单位了解项目情况及后续建设计划 | Y26: 项目施工招标阶段 | Z26: 1.8月27日设计招标已开标， 2.8月29日已公示入围单位。 3.9月24日，中交第二公路勘察设计研究院有限公司中标项目设计 4.3月31日，项目已发布招标计划，计划4月底进行施工招标 | AA26: 一般信息（Ⅲ级） | AB26: 唐作栋 | AE26: 唐作栋 | AF26: 跟进中 | AG26: 唐作栋
A27: 46112 | B27: 2025-08-31 18:57:41 | C27: XM-2025083120211 | D27: 庄河核电厂循环水进水管道与排水管道隧道 | F27: 庄河核电厂一期工程每台机组设置 2 条循环水进水管道(GD)，循环水进水管道(GD)采用现浇钢筋混凝土管道内衬玻璃钢管道，内径尺寸为 4000mm；庄河核电厂一期工程每台机组设置 2 条循环水排水管道(GE)，循环水排水管道(GE)采用现浇钢筋混凝土管道内衬玻璃钢管道，内径尺寸为 4750mm | G27: 庄河核电厂一期工程每台机组设置 2 条循环水进水管道(GD)、 2 条循环水排水管道(GE) | H27: 其他-13 | I27: 掘进机事业部 | J27: 华东区域 | L27: 辽宁 | M27: 3,200.0000000000 | N27: 中核大唐庄河核电有限公司 | O27: 中国核电工程有限公司 | P27: 核工业井巷建设集团有限公司 | Q27: ZTT5500-1-(/);/-1-(/); | R27: 2026-06-30 | S27: CNY 30,000,000.000 | T27: 唐作栋 | W27: 3月已与核工业井巷公司进行两次技术交流，拟就非全断面连续开挖设备技术申报浙江省“尖兵”、“领雁”科研项目，目前正在进行开题报告复核，并在第二批指南中进行申报。 | X27: 核工业井巷公司拟在起其建项目中寻找一个项目，试用我司EBM设备，考察设备实用性及可靠性。 | Y27: 商务交流 | Z27: 3月已与核工业井巷公司进行两次技术交流，拟就非全断面连续开挖设备技术申报浙江省“尖兵”、“领雁”科研项目，目前正在进行开题报告复核，并在第二批指南中进行申报。 | AA27: 一般信息（Ⅲ级） | AB27: 唐作栋 | AE27: 唐作栋 | AF27: 跟进中 | AG27: 唐作栋
A28: 46112 | B28: 2025-09-28 22:31:42 | C28: XM-2025092820433 | D28: 新建上海至杭州高速铁路（沪杭高铁） | F28: 线路起自上海东站，经嘉兴进入杭州市，终至杭州西站，全线运营长度220.9km，新建线路长度182.0km，其中嘉兴境内约100公里，设平湖南、嘉兴南、桐乡三座车站。 | G28: 无隧道 | H28: 铁路-2 | I28: 特种装备事业部 | J28: 华东区域 | L28: 浙江 | M28: 400.0000000000 | N28: 杭州铁路枢纽工程建设指挥部 | O28: 中国铁路设计集团有限公司 | Q28: HZS180K-2-(/); | R28: 2026-06-30 | S28: CNY 5,000,000.000 | T28: 唐作栋 | W28: 1月14日开始施工图审查招标，施工招标26年2季度进行 | X28: 拜访业主单位，了解后续招标计划 | Y28: 项目施工招标阶段 | Z28: 1月14日开始施工图审查招标，施工招标26年2季度进行 | AA28: 一般信息（Ⅲ级） | AB28: 唐作栋 | AE28: 唐作栋 | AF28: 跟进中 | AG28: 唐作栋
A29: 46112 | B29: 2023-08-26 22:48:07 | C29: XM-2023082614800 | D29: 巴东至张家界高速沪蓉沪渝连接线项目 | F29: 巴东至张家界高速沪蓉沪渝连接线（含巴东长江二桥）起于巴东县城北侧与沪蓉高速公路设枢纽互通相接，向南跨长江，经巴东县茶店子镇、秭归县磨坪乡，止于巴东县野三关镇关镇西侧与沪渝高速公路设枢纽互通相接，路线全长约70.596km。巴东城区北互通连接线全长约4km，磨坪互通连接线长约4.3km，两处连接线均按二车道二级公路标准建设。桥梁全长16250m/35座（其中：特大桥6290m/4座，大桥9870m/30座，中桥90m/1座，其中巴东长江公路二桥主桥推荐采用主跨1150m钢箱梁悬索桥）。隧道全长40511m/16座（其中：特长隧道26743m/5座（其中信陵隧道长度10082m），长隧道11610/7座，中隧道1515/2座，短隧道643/2座）。设互通式立交7处（巴东高铁新区互通、溪丘湾枢纽、巴东城区北互通、巴东城区南互通、秭归磨坪互通、野三关北互通、野三关枢纽）、养护工区1处，服务区1处，路段管理分中心1处。技术标准：全线拟采用80km/h设计速度，四车道的高速公路设计标准，路基宽25.5m，长江大桥采用双向六车道标准。本项目估算总金额约为201亿元。 | G29: 隧道全长40511m/16座（其中：特长隧道26743m/5座（其中信陵隧道长度10082m），长隧道11610/7座，中隧道1515/2座，短隧道643/2座）。 | H29: 公路-4 | I29: 特种装备事业部 | J29: 华东区域 | K29: 华中区域 | L29: 湖北 | M29: 201.0000000000 | N29: 湖北交通投资集团有限公司 | Q29: ZY112B-2-(2026-06-01); | R29: 2026-06-30 | S29: CNY 5,000,000.000 | T29: 万赛 | W29: 3月23日从十九华东公司了解到该项目计划6月份启动。 | X29: 持续跟进，了解设备具体需求时间。 | Y29: 项目施工中标公示 | Z29: 1、核心问题：目前还未正式明确所需大机配套设备； 2、工作思路：已经要求客户到我司考察大机配套设备及技术交流； 3、关键点：项目设计还有部分为完成，项目启动资金也还未到位； 4、行动计划：时刻保持与公司及项目部的对接工作，配合该项目做好大机配套方案。 | AA29: 重点信息（Ⅱ级） | AB29: 万赛 | AE29: 万赛 | AF29: 跟进中 | AG29: 万赛
A30: 46112 | B30: 2025-03-28 09:13:07 | C30: XM-2025032819047 | D30: 宁波枢纽建设工程绕城高速改扩建项目 | F30: 起于古中路与绕城高速的交叉点，止于朝阳互通。路线全长9.4km，隧道长度5.2km，其中盾构段长度3.65km，设置2座通风塔。 | G30: 其中盾构段长度3.65km，拟采用16米级盾构机 | H30: 公路-4 | I30: 掘进机事业部 | J30: 华东区域 | L30: 浙江 | M30: 170.0000000000 | N30: 宁波市高等级高速公路建设 | O30: 待定 | P30: 待定 | Q30: 待定-1-(/); | R30: 2028-09-13 | S30: CNY 250,000,000.000 | T30: 沈腾飞 | W30: 目前已对接西枢纽和市铁办建设管理中心一处处长，项目可研阶段，拟采用盾构施工，计划近期拜访宁波西枢纽和市铁办建设管理中心前期处处长，项目规划阶段，拟采用盾构施工，考虑16米盾构方案概率较小，拟高架或明挖。项目规划中，暂无进展 | X30: 拜访业主单位及前期设计单位，梳理项目最新进展。 | Y30: 项目立项阶段（预可研，初测及可研，环评） | Z30: 核心问题：1、采用多大直径盾构机施工方案还未明确；2、最终业主单位还未明确 行动计划：拜访西枢纽管理中心前期规划处领导，了解项目情况，组织方案交流事宜。 | AA30: 重大信息（Ⅰ级） | AB30: 沈腾飞 | AE30: 沈腾飞 | AF30: 跟进中 | AG30: 沈腾飞
A31: 46112 | B31: 2021-10-22 22:28:26 | C31: XM-202110228391 | D31: 宁波至余慈市域（郊）铁路二期 | F31: 全长53.95km，全线新建车站13座，其中余姚段21km | G31: 暂未确定 | H31: 轨道交通 | I31: 掘进机研发运营中心 | J31: 华东区域 | L31: 浙江 | M31: 250.0000000000 | N31: 宁波轨道交通集团 | Q31: ZTE8600-4-(2026-07-22); | R31: 2026-05-13 | S31: CNY 30,000,000.000 | T31: 沈腾飞 | U31: 万赛 | W31: 目前项目未获批，宁象宁慈线盾构设备明年全部贯通，盾构机会用到该项目继续施工。 | X31: 跟进项目工可获批情况，预计2027年获批！ | Y31: 项目立项阶段（预可研，初测及可研，环评） | Z31: 核心问题：隧道施工潜在中标单位中铁工一/二/三/四/隧道局,铁建重工十四/十九局，系统为争取单位：中铁隆/宁波建工/龙元建设。 工作思路：配合系统内单位投标，充分利用供应链公司介入设备租赁 关键点：设备租赁价格8000-9000元/米，价格较低 行动计划：跟踪项目进展，了解区间划分情况。预计2025年启动先行标招标。 | AA31: 一般信息（Ⅲ级） | AB31: 沈腾飞 | AE31: 余广 | AF31: 跟进中 | AG31: 沈腾飞
A32: 46112 | B32: 2023-07-30 11:38:46 | C32: XM-2023073014507 | D32: 甬江流域南排通道工程 | F32: 西线工程总长约57.8公里，主要采用13米级TBM/双模盾构、土压盾构法和钻爆法进行施工。东线工程总长约42.2公里，主要采用13米级土压盾构法、13米级TBM/双模盾构和钻爆法进行施工。此外，全线设计有7口竖井，深度为45米，直径在23米至25米之间，采用竖井掘进机进行施工。 | G32: 隧道长度16km，拟采用9米敞开式TBM施工，主要以2.3类围岩为主，4.5类围岩占比15% | H32: 水利水电-0 | I32: 掘进机事业部 | J32: 华东区域 | L32: 浙江 | M32: 50.0000000000 | N32: 宁波市水库管理中心 | O32: 项目建议书为宁波市水利水电规划设计院 | P32: 待定 | Q32: 8米敞开式TBM-1-(/); | R32: 2026-01-05 | S32: CNY 140,000,000.000 | T32: 沈腾飞 | W32: 1.11月可研挂网招标，预计中标单位浙江水院和宁波水院； 2.宁波将项目列入十五五重点启动项目，前期启动； 3、3月31日已对接8米TBM同步衬砌事宜，节后技术交流。周公宅与亭下之间新建分洪隧洞启动较快 | X32: 1.同宁波水院交流8米TBM掘进衬砌同步技术，竖井布置情况等； 2.拜访浙江省水院设计负责人； 3.邀请宁波水利局到我司或大盾构项目考察。 | Y32: 项目立项阶段（预可研，初测及可研，环评） | Z32: 核心问题：项目建议书阶段，投资200亿元，是否最终获批 工作思路：告知系统内单位，共同跟进，配合项目建议书单位编制项目建议书 关键点：是否采用大盾构/TBM施工方案 行动计划：跟踪项目进展，配合浙江省水院设计院做前期项目建议书。目前项目建议书暂未批复。 | AA32: 重点信息（Ⅱ级） | AB32: 沈腾飞 | AE32: 沈腾飞 | AF32: 跟进中 | AG32: 沈腾飞
A33: 46112 | B33: 2024-10-27 12:47:44 | C33: XM-2024102718062 | D33: 甬金衢上高速公路台州段 | F33: 甬金衢上高速台州段工程路线起点设置仆船隧道内与绍兴段顺接，隧道出口后设置石梁互通及连接线，过后设置天台山1号隧道（分离式左线长9470m），进洞后路线转向西南，出洞后设置桥梁后再次进入隧道，出洞后进入天台盆地，路线继续向西于白鹤镇南端设置白鹤枢纽与上三高速交叉，跨越上三高速和104国道后，于楼外村附近设置互通与104国道相接，之后向西下穿杭绍台高铁，路线向西于上坝头村附近上跨合溪干渠，在王里溪村附近设置平桥互通及连接线与323省道连通，向西沿山脚布线，于合溪口村西侧跨越合溪，向西在杭绍台高速天台街头互通北侧上跨既有杭绍台高速，并设置街头枢纽与杭绍台高速交叉，路线继续向西沿山脚布线在后洋村附近设置街头互通与连接线与323省道连通，路线沿杨家溪南岸，沿峡谷地带靠山侧布线，采用路基为主的方案进入山区，设置庄家岙隧道、寒山湖隧道，至寒山湖隧道内台州与金华交界处与甬金衢上高速金华段顺接，路线全长约46.6km。项目估算总投资约156.7亿元，其中建安费约93.5亿元。本项目设桥梁长约12678米／30座；隧道长约18680米／6座（其中特长隧道2座、长隧道2座）；主线设枢纽2处（白鹤枢纽、街头枢纽）；互通及收费站4处（石梁互通、天台北互通、平桥互通、街头互通）；服务区1处（平桥服务区）；设置隧道管理站2处；共设置石梁互通、平桥互通与街头互通3条连接线。全线采用双向六车道高速公路设计标准，其中起点至白鹤枢纽、街头互通至终点段采用设计速度100km/h，路基宽度33.5m；白鹤枢纽至街头互通段约20km采用设计速度120km/h，路基宽度34.0m。 | G33: 隧道长约18680米／6座（其中特长隧道2座、长隧道2座） | H33: 公路-4 | I33: 特种装备事业部 | J33: 华东区域 | L33: 浙江 | M33: 93.5000000000 | N33: 天台县交通运输局 | O33: 招标中 | P33: 待定 | Q33: HZS1800-2-(2026-06-30); | R33: 2026-07-08 | S33: CNY 3,000,000.000 | T33: 沈腾飞 | W33: 数字交院中标设计，目前设计中，本标段天台县交通局出资30%，省交投出资70%，共计四个标段 2月24日拜访设计院，了解到：因业主资金未到位，设计暂停中。天台交通局暂无资金来源，还要同省交通沟通资金情况。业主同时开展其他资金引入的工作本标段天台县交通局出资30%，省交通出资70%。 | X33: 1.计划4月10日前拜访天台交通局，了解项目进展，标段划分，推荐大机配套 | Y33: 施工图设计阶段 | Z33: 核心问题：1、业主单位是否要求机械化施工；2、拨付机械化施工补贴 工作思路：引导业主单位推广机械化施工 关键点：业主是否愿意出资使用机械化设备。 行动计划：1、筹划拜访业主单位、设计单位，引导机械化施工。 | AA33: 一般信息（Ⅲ级） | AB33: 沈腾飞 | AE33: 沈腾飞 | AF33: 跟进中 | AG33: 沈腾飞
A34: 46112 | B34: 2025-04-28 09:17:32 | C34: XM-2025042819285 | D34: 宁波象山港北岸配水（一期）工程Ⅰ标段 | F34: （1）新建蒋家池头至大嵩水厂引（输）水管线，其中主管线长约 16.9 千米。输水线由蒋家池头调节站始发，向东偏北以顶管（1#管道，长约 221 米）依次下穿莼湖快速路、金溪后，在张家墈转 1#隧洞（长约 4.26 千米）下穿金娥山，在车岭水库南侧山体出洞。再次以顶管（2#管道，长约 659 米）下穿下潘村后，转入 2#隧洞（长约 11.62 千米）穿越横岭山、梅溪，甬绍东天然气管、地铁12号线，在经堂寺南侧山体出洞 | G34: 11.62 千米引水隧道，拟采用4米敞开式TBM | H34: 水利水电-0 | I34: 掘进机事业部 | J34: 华东区域 | L34: 浙江 | M34: 9.0000000000 | N34: 宁波市水利投资有限公司 | O34: 电建华东院 | P34: 广东省建筑工程集团股份有限公司;禹顺生态建设有限公司 | Q34: ZTT4030-1-(2027-01-05); | R34: 2026-05-11 | S34: CNY 30,000,000.000 | T34: 沈腾飞 | W34: 1.10月14日拜访宁波水投工程技术部，项目可研审批中，计划元旦前招标。 2.浙江隧道已中标东西线水库联通工程，设备型号一致，且项目完成业主较认可，中标概率较大。 3.12月11日拜访宁波水投工程主管，项目可研近期批复，预计2026年2-3月招标。 4、1月20日施工招标，2月10日投标截止，目前中铁十八局、十九局业绩满足。 核实设备需求时间为 2026 年 8 月，计划 10—11月实现始发。设备拟由禹顺生态采购 4 米级 TBM，并计划租赁给广东省粤水电用于施工。3 月中旬及下旬，与禹顺生态柴总进行了两次沟通交流，目前主要竞争对手为中铁装备，安徽唐兴、华隧。3 月 28 日已向禹顺生态提交设备报价及配置参数资料。禹顺生态计划于 3 月底组织外部专家对各单位提交的参数方案进行评审，预计 4 月上旬确定设备中标单位。3月30日获悉华隧自有一台设备且带施工，粤水电不参与施工、仅收取管理费，禹顺自负盈亏。粤水电负责项目的设备招采流程（租赁） 3月底客户已告知业主租赁TBM。 | X34: 1、了解租赁招标流程，启动时间等； 2、梳理TBM资源，价格等，再决策是否参与投标 | Y34: 项目施工招标阶段 | Z34: 1.10月14日拜访宁波水投工程技术部，项目可研审批中，计划元旦前招标。 2.浙江隧道已中标东西线水库联通工程，设备型号一致，且项目完成业主较认可，中标概率较大。 3.12月11日拜访宁波水投工程主管，项目可研近期批复，预计2026年2-3月招标。 4、1月20日施工招标，2月10日投标截止，目前中铁十八局、十九局业绩满足。 5.2月11日广东省建筑工程集团股份有限公司;禹顺生态建设有限公司施工中标。6.目前禹顺、金华井巷、粤水电（刘畅）及其他两家民企目前均说需要采购新机，已让研究院欧佳君在做方案，下周一给出配置方案，目前统一TBM口头报价4000万元，最终以事业部给出价格为准。 | AA34: 一般信息（Ⅲ级） | AB34: 沈腾飞 | AE34: 沈腾飞 | AF34: 跟进中 | AG34: 沈腾飞
A35: 46112 | B35: 2024-07-09 16:48:49 | C35: XM-2024070917264 | D35: 乌岩港大桥及接线公路工程 | F35: 乌岩港大桥及接线公路工程项目为二级公路，起点位于鹤浦镇黄岩庄，与石三线十字交叉，沿线途经黄金盘、楼屋、大湾塘、小外湾等村庄，在后龙头村南侧跨越乌岩港进入高塘乡，终点接石三线引桥桥头。路线全长约10.567km，采用双向两车道二级公路标准，设计速度60km/h，路面采用沥青混凝土路面。项目预计于2026年动工开建，计划建设周期36个月。 | G35: 1.77km特大桥。 | H35: 公路-4 | I35: 特种装备事业部 | J35: 华东区域 | L35: 浙江 | M35: 10.0000000000 | N35: 象山县交投 | O35: 宁波市交通规划设计院 | P35: 暂定中铁建大桥局三公司 | Q35: 180-2-(2026-06-30); | R35: 2026-09-01 | S35: CNY 3,000,000.000 | T35: 沈腾飞 | U35: 万赛 | W35: 目前设计阶段，已拜访中铁建大桥局宁波办事处，项目拟需求两套海工180搅拌站，铁建大桥三公司跟踪中标概率较大。目前初步设计暂未获批。因资金未到位，项目推迟到2026年下半年。暂无最新进展 | X35: 跟进并配合系统等潜在中标单位投标。 | Y35: 项目施工招标阶段 | Z35: 核心问题：因桥墩在海中施工，混凝土要求较高，业主采购新设备 工作思路：配合系统内单位投标 关键点：系统内单位中标概率较大，铁建大桥局三公司项目经理业主较认可 行动计划：配合大桥局项目投标，提前沟通搅拌站需求。初步设计暂未获批，资金仍未到位。 | AA35: 一般信息（Ⅲ级） | AB35: 沈腾飞 | AE35: 沈腾飞 | AF35: 跟进中 | AG35: 沈腾飞
A36: 46112 | B36: 2025-06-27 09:01:24 | C36: XM-2025062719731 | D36: 机场路(通途西路-规划空港大道)综合管廊工程 | F36: 机场路(通途西路-规划空港大道)综合管廊工程位于海曙区，北起通途西路管廊预留工作井，南至规划空港大道，全长约9.6公里。管廊规划基本位于道路两侧防护绿带内，标准段采用圆形盾构断面形式(分高压舱和综合舱)，规划预留电力、再生水、给水、压力污水、通信等管位入廊空间。 | G36: 9.6公里，采用ZTE6950盾构机施工 | H36: 市政管廊-6 | I36: 掘进机事业部 | J36: 华东区域 | L36: 浙江 | M36: 11.7500000000 | N36: 宁波城市地下空间投资有限公司 | O36: 宁波建筑设计院 | P36: 宁波建工建乐 | Q36: ZTE6950-2-(/); | R36: 2026-05-13 | S36: CNY 10,000,000.000 | T36: 沈腾飞 | W36: 2025年12月16日中标公示，1标中标单位宁波建工建乐+中铁六局；2标中标单位中铁隧道局，自有改造设备，预计需求时间2026年12月。 | X36: 1.了解宁波建工建乐设备需求时间，设备要求；2.了解盾构分包模式。 | Y36: 设计联络 | Z36: 拜访中铁隧道局及宁波建工建乐，了解设备需求情 | AA36: 一般信息（Ⅲ级） | AB36: 沈腾飞 | AE36: 沈腾飞 | AF36: 跟进中 | AG36: 沈腾飞
A37: 46112 | B37: 2025-06-27 08:55:23 | C37: XM-2025062719730 | D37: 环城南路(联丰中路-世纪大道)综合管廊工程 | F37: 环城南路(联丰中路-世纪大道)综合管廊工程位于海曙区、鄞州区，西起联丰中路，东至世纪大道，全长约13公里。管廊规划基本位于道路两侧防护绿带内，标准段采用圆形盾构断面形式(分高压舱和综合舱)，规划预留电力、再生水、给水、压力污水、通信等管位入廊空间。 项目规模：估算总投资约259492.01万元,其中工程费用约170046.97万元。 | G37: 全长约13公里，采用6.7米土压平衡盾构机掘进 | H37: 市政管廊-6 | I37: 掘进机事业部 | J37: 华东区域 | L37: 浙江 | M37: 17.0000000000 | N37: 宁波城市地下空间投资有限公司 | O37: 上海市政院 | P37: 待定 | Q37: ZTE6950-4-(/); | R37: 2026-04-14 | S37: CNY 10,000,000.000 | T37: 沈腾飞 | W37: 上海市政院中标设计。目前设计中。暂定3个标段，11月6日施工招标审查预公告，11月12日招标资格预审查，12月18日中标结果:中铁二十二局+中铁十局，宁波市政+铁四局，中交水电+中天建设，中天建设施工盾构区间，自有2台海瑞克设备。宁波市政区间长度5km，拟考虑采购一台旧机，3月23日已报价。 | X37: 1.跟踪宁波市政向领导汇报情况，后续再组织设备考察及交流；5月15日前完成 2、了解宁波建工建乐和中铁六局分工情况，4月30日前完成。 | Y37: 设计联络 | Z37: 已拜访业主单位及部分潜在中标设计单位 | AA37: 一般信息（Ⅲ级） | AB37: 沈腾飞 | AE37: 沈腾飞 | AF37: 跟进中 | AG37: 沈腾飞
A38: 46112 | B38: 2023-07-30 11:03:50 | C38: XM-2023073014506 | D38: 台州市中心大道路过江通道 | F38: 台州市椒江城市发展投资集团有限公司投资的世纪大道路过江隧道，隧道长度2.1km，由椒江区投资，项目已立项完成，采用16.3米泥水平衡盾构机。 | G38: 隧道长度2.1km，拟采用16.3米泥水盾构机施工 | H38: 城建-1 | I38: 掘进机事业部 | J38: 华东区域 | L38: 浙江 | M38: 28.0000000000 | N38: 台州市椒江城市发展投资集团有限公司 | O38: 湖南交规院 | P38: 待定 | Q38: 泥水平衡盾构机-1-(2026-12-07); | R38: 2026-12-04 | S38: CNY 200,000,000.000 | T38: 沈腾飞 | W38: 1.2025年6月拜访设计单位及项目专班，交流盾构机选型； 2.跟踪初步审查进展，2025年11月已完成初步审查； 3、资金来源采用专项债，目前到账3亿元，已启动前期道路项目； 4、预计2026年2季度施工招标； 5.隧道延米设计概算42万元/米； 6.目前台州市政府拟改造一桥，项目存在推迟风险，预计2026年下半年施工招标。 | X38: 1.了解代建单位招标时间、招标条件设置、业主资金到位情况等； 2.配合十四局接待业主到海太项目考察。 | Y38: 施工图设计阶段 | Z38: 核心问题：1.设计阶段、施工方暂未明确；2、盾构机区间约2km，大概率设备租赁。3.中铁隧道局正在施工解放路过江隧道，如投标，有较大价格优势。 工作思路：配合系统内单位共同跟进项目进展，拜访业主，核实业主对设备新旧等要求。 关键点：设备市场存有量较大，业主暂定设备新制，是否会被变更。 行动计划：拜访业主单位，配合系统内单位跟踪项目进展。 | AA38: 重点信息（Ⅱ级） | AB38: 沈腾飞 | AE38: 沈腾飞 | AF38: 跟进中 | AG38: 沈腾飞
A39: 46112 | B39: 2024-12-30 20:33:31 | C39: XM-2024123018583 | D39: 中铁二十一局集团川气东送项目 | F39: 该项目其中温州市区和瑞安市区有下穿瓯江和飞云江盾构段，长度分别为918米、737米。隧道断面分别为4.25米、3.08米。预计需求两台不同直径泥水盾构，需进一步了解施工单位设备来源。 | G39: 其中温州市区和瑞安市区有下穿瓯江和飞云江盾构段，长度分别为918米、737米。 | H39: 其他-13 | I39: 掘进机事业部 | J39: 华东区域 | L39: 浙江 | M39: 10.0000000000 | N39: 国家石油天然气管网集团有限公司西气东输分公司 | Q39: ZTS5040-1-(/);ZTS3770-1-(/); | R39: 2025-06-30 | S39: CNY 8,000,000.000 | T39: 袁志凌 | W39: 目前施工已中标，中标单位为中铁二十一局路桥公司，项目部正在选址；其中温州市区和瑞安市区有下穿瓯江和飞云江盾构段，长度分别为918米、737米。已与项目部进行交流洽谈，目前因市面上没有合适机型暂未确认设备来源，21局拟采用劳务专业分包，由分包队带设备，目前还在队伍洽谈中。暂无新进展。 该项目已于河北某劳务队洽谈设备租赁，由于未签订合同，项目部暂未告知公司名称。 项目已明确轨道公司分包劳务。设备拟采用安徽唐兴旧机维修改造。 | X39: 了解拟租设备及租赁合同价格 | Y39: 设计联络 | Z39: 已与项目部总工、设备部长对接，并邀请业主、设计和项目部到公司考察。由于隧道短，客户拟采用安徽唐兴旧机维修改造。 | AA39: 一般信息（Ⅲ级） | AB39: 袁志凌 | AE39: 袁志凌 | AF39: 跟进中 | AG39: 袁志凌
A40: 46112 | B40: 2024-03-11 11:18:15 | C40: XM-2024031116383 | D40: 中铁二十二局义龙庆7标项目部 | F40: 本项目主线右幅YK176+700～YK186+560段长约9.86公里、左幅ZK176+700～ZK186+550段长约9.85公里的路基、桥梁（含伸缩缝安装）、涵洞、隧道（含高位水池，不含隧道机电）、改路改河改渠（含改路路面）等的实施、完成、缺陷责任期缺陷修复等 | G40: 大淤山隧道：1475m；大丘田隧道：3452.5m | H40: 公路-4 | I40: 特种装备事业部 | J40: 华东区域 | L40: 浙江 | M40: 200.0000000000 | N40: 浙江省高速建设管理有限公司 | Q40: SCC2000-1-(/); | R40: 2024-08-20 | S40: CNY 16,000,000.000 | T40: 袁志凌 | W40: 已与项目业主和施工单位开展了技术交流和设备需求了解，该项目拟采用劳务专业分包，根据客户描述：由于设备昂贵，垫资成本过高，劳务队不能接受设备施工，目前项目部还在与劳务队沟通中 | X40: 跟进除尘台车需求，了解需求时间及设备考虑情况 继续跟进除尘台车需求 跟进是否有除尘台车需求 核实是否还有除尘台车采购需求 | Y40: 项目施工中标公示 | Z40: 核心问题：业主交代必须使用进口凿岩台车，设备基本由劳务队自带，劳务队更多考虑价格偏低厂家，我司设备没有价格和明显技术优势 工作思路：跟进好各标段劳务队设备需求及意向情况，联同研究院与其进行交流，凸显我司产品特征优势，紧密对接好部分有我司产品采购意向的单位和劳务队； 关键点：该项目智能化设备应用程度高，部分标段目前仍未确定采购进口凿岩台车，我司需紧密动态对接和跟进； 行动计划：联合研究院逐项对接项目部和劳务队，摸排劳务队设备持有及需求情况。 | AA40: 重点信息（Ⅱ级） | AB40: 袁志凌 | AE40: 袁志凌 | AF40: 跟进中 | AG40: 袁志凌
A41: 46112 | B41: 2023-10-31 22:50:29 | C41: XM-2023103115374 | D41: 甬舟高速公路复线二期 | F41: 甬舟高速公路复线起于宁波北仑好思房，经金塘岛、册子岛、富翅岛至舟山本岛，近期终于定海大沙，接北向疏港公路，路线总长约45.5km。 戚家山-金塘段：长18.038km，目前处于工可阶段。 隧道全长11.644km，含盾构段9.89km（其中陆域盾构段1.3km，海中盾构段8.59km），钻爆段1.159km，明挖段0.595km。 | G41: 隧道全长11.644km，含盾构段9.89km（其中陆域盾构段1.3km，海中盾构段8.59km），钻爆段1.159km，明挖段0.595km。 | H41: 公路-4 | I41: 掘进机事业部 | J41: 华东区域 | L41: 浙江 | M41: 45.0000000000 | N41: 舟山甬舟铁路建设指挥部、浙江交建 | O41: 浙江省数智交院、铁四院 | P41: 待定 | Q41: 泥水平衡盾构机-1-(2026-10-29); | R41: 2025-10-29 | S41: CNY 500,000,000.000 | T41: 袁志凌 | U41: 沈腾飞 | V41: 设备已中标 | W41: 8月21日中标结果公示中，1标中铁十四局+浙交工地下公司；3标中交隧道；2标中铁隧道+宁波交工。中铁十四局拟采用京华号再制造。 采用7.6米主轴承。业主10月31日召开会议，要求各施工单位于11月15日确定盾构厂家，11月30日设备启动生产；中铁十四局再制造报价中；浙江交工地下近几天邀请盾构机招标。 浙江交工地下公司已于11月28日邀请招标。暂未明确中标单位。 目前我司得分最高，但暂未公开中标结果 已完成设计参数和主要零部件品牌确认 已完成第一次设计联络，并通过 已完成第二次设计联络 | X41: 完成合同签订及三方协议签订 | Y41: 项目施工中标公示 | Z41: 核心问题：1.系统内单位是否能中标该项目；2.盾构机生产周期比较紧 工作思路：项目持续跟进，配合铁建单位中标。策划高层互动。 关键点：代建单位同中铁装备在杭州有盾构公司，双方合作中，代建单位对设备选择有较大影响。铁建单位中标情况。 行动计划：跟进建设单位，参与前期设备选型，拜访代建单位，提前关系介入，组织考察交流，策划高层互动。配合系统内单位及股份公司争取铁建系统单位中标。 | AA41: 重点信息（Ⅱ级） | AB41: 沈腾飞 | AE41: 沈腾飞 | AF41: 跟进中 | AG41: 袁志凌
A42: 46112 | B42: 2024-03-02 21:13:37 | C42: XM-2024030216332 | D42: 浙江柯城抽水蓄能电站 | F42: 总投资约80.72亿元，装机容量120万千瓦。电站枢纽工程主要由上水库、下水库、输水系统、地下厂房和开关站等建筑物组成，按装机容量确定为一等大（1）型工程，建成后主要承担浙江电网的调峰、填谷、储能、调频、调相和备用等任务。前期标Q1标：目前已挂网招标，主要包括，连接公路、检修平台、进场交通洞600米、通风安全洞1.2公里 断面大小6.5x7.5米；施工支洞合计7个洞长合计3195米，断面大小从8.0x8.5到3.0x3.0不等；开标时间为10月14日；10月31日定标为水电十二局 | G42: 进场交通洞、排水廊道 | H42: 水利水电-0 | I42: 掘进机事业部 | J42: 华东区域 | K42: 西南区域 | L42: 浙江 | M42: 80.7200000000 | N42: 浙江柯城抽水蓄能有限公司 | O42: 中国电建集团华东勘测设计研究院有限公司 | P42: 水电五局 | Q42: 开挖直径3.5米级TBM-1-(/); | R42: 2026-06-30 | S42: CNY 30,000,000.000 | T42: 刘新峥 | W42: 1、同掘进机、特装事业部拜访业主工程部刘岗、姜卫海一行进行技术交流；_x005f?2、业主反馈不会增加费用要求施工单位上智能化设备。?3、业主对科研创新项目感兴趣，尤其是针对斜井作业台车，同事业部郑松出具科研项目立项书，上报业主；?4、后续业主反馈，该设备无实际案例，出具安全考虑，未能申报成功。 5、目前已挂网招标，共分为上库、下库、输排水系统，12月8日开标。 6、目前系统内单位十八局已报名参与1、同掘进机、特装事业部拜访业主工程部刘岗、姜卫海一行进行技术交流；?2、业主反馈不会增加费用要求施工单位上智能化设备。?3、业主对科研创新项目感兴趣，尤其是针对斜井作业台车，同事业部郑松出具科研项目立项书，上报业主；?4、后续业主反馈，该设备无实际案例，出具安全考虑，未能申报成功。 5、目前已挂网招标，共分为上库、下库、输排水系统，12月8日开标。 6、目前系统内单位十八局已报名参与 | X42: 1、拜访业主单位针对竖井掘进机再进行技术交流汇报；竖井已明确租用水电十二局松阳抽蓄旧设备 2、跟进斜井作业平台 | Y42: 商务交流 | Z42: 核心问题：业主不会强制要求施工单位采用机械化施工；3.53米TBM目前我司没有租赁设备。 工作思路：全力跟进业主方，邀请其到我司参观考察TBM设备，全力推进斜井作业平台的科研合作事宜。 关键点:主体标施工中标单位，是否认可我司产品，是否自有该型号设备。 行动计划：协作业主工程部报批科研合作项目，节后再次拜访业主单位，详谈具体的合作模式、 | AA42: 重点信息（Ⅱ级） | AB42: 刘新峥 | AE42: 刘新峥 | AF42: 跟进中 | AG42: 刘新峥
A43: 46112 | B43: 2024-12-30 15:45:19 | C43: XM-2024123018580 | D43: 绍兴市城市轨道交通4号线1标 | F43: 工程位于浙江省绍兴市越城区。包独树路站/独树路站～银桥路站区间/银桥路站总共2站1区间、银桥路站站后区间及泄压井： (1)独树路站为地下二层岛式站，长183.3m，宽19.7m，深约16.59m。附属设1个出入口。 (2)银桥路站为地下二层岛式站，长259.6m，宽19.7m，深约17.42m。附属4个出入口，4组风亭，3个安全出入口。 (3)独树路站～银桥路站区间右线1556.858m，左线1556.658m，联络通道2座。 (4)银桥路站站后区间左/右线长均为150.891m，不设联络通道。 (6)配套的桥梁拆复建1座、绿化迁移、管线迁改、交通导改等施工内容。 区间隧道管片外径6.7m，采用2台土压盾构机施工。 工期1946个日历天，开竣工日期2024年12月31日～2030年04月30日。 | G43: 独树路站～银桥路站区间右线1556.858m，左线1556.658m，联络通道2座。 (4)银桥路站站后区间左/右线长均为150.891m，不设联络通道。 (6)配套的桥梁拆复建1座、绿化迁移、管线迁改、交通导改等施工内容。 | H43: 地铁-5 | I43: 掘进机事业部 | J43: 华东区域 | L43: 浙江 | M43: 4.9200000000 | N43: 绍兴市轨道交通集团有限公司 | O43: 中铁二院 | Q43: ZTE6950-2-(/); | R43: 2026-03-31 | S43: CNY 17,000,000.000 | T43: 刘新峥 | W43: 1、项目25年5月25日正式开始打桩，预计26年5月份具备始发条件； 2、项目部已完成询价，询价结果如下：我司6500、武重机床5500、十一局一公司4800、广州山河4000、交工地下3390，中铁工服3700 3、11月拜访项目部，其计划使用11局四公司厦工中铁设备及租赁十五局轨道公司DZ1001（租赁价格3500元/米）。 | X43: 1、对接华中区域郭统佳，了解十一局四公司设备情况是否满足业主的招标条件。 2、十五局1001预计需求改造刀盘及盾尾，对接华中区域车成，跟进十五局的设备维修需求。 | Y43: 商务交流 | Z43: 核心问题：目前绍兴市场不限盾构机品牌，设备租入价格基本在4000元/米以下，我司目前报价略高，十一局有类似型号设备，且自己具备维修改造能力。 工作思路：同十一局城轨公司及项目部积极交流方案，汇报实际情况，协同华中区域协调事业部，尽量给出合理报价；与目前市面上的租赁单位尽量达成一致，避免恶性竞争。 关键点：抓住十一局为系统内单位的点，明确其是否使用自有设备 行动计划：拜访项目部汇报技术方案，前期做好技术配合，提前与事业部沟通，汇报绍兴市场的盾构机租赁价格。 | AA43: 一般信息（Ⅲ级） | AB43: 刘新峥 | AE43: 刘新峥 | AF43: 跟进中 | AG43: 刘新峥
A44: 46112 | B44: 2024-12-30 15:51:47 | C44: XM-2024123018581 | D44: 绍兴市地铁5号线 | F44: 线路全长约15.3公里，共设站12座，均为地下站，其中换乘站3座；新建袍中路车辆段1座；新建出入段线2条 | G44: 线路全长约15.3公里，共设站12座，均为地下站，其中换乘站3座；新建袍中路车辆段1座；新建出入段线2条 | H44: 地铁-5 | I44: 掘进机事业部 | J44: 华东区域 | L44: 浙江 | M44: 103.6800000000 | N44: 绍兴市轨道交通集团有限公司 | Q44: ZTE6950-16-(/); | R44: 2027-06-30 | S44: CNY 20,000,000.000 | T44: 刘新峥 | W44: 前期标中标单位为北京城建院，目前总设正在招标，目前已延期开标，开标时间另行通知，预计推后至26年开标‘’ | X44: 拜访业主单位灌输高端品牌理念，提前对接供应链公司争取提前嫁接。 | Y44: 施工图设计阶段 | Z44: 核心问题：业主方对设备要求宽泛，不限制品牌，导致市场价格过低 工作思路：引导业主单位，注重项目建设品质，对设备设置门槛；与业主单位探讨是否可以复刻宁波地铁模式，使多方获利； 关键点：绍兴地铁多次选用辽宁三三等品牌设备，要打破其价格至上的思维。 行动计划：有节奏的拜访业主单位，向其灌输隧道施工设备的重要性，尽量在后续项目中提高对设备的要求；介绍宁波地铁经营模式，给业主单位提供新思路； | AA44: 重点信息（Ⅱ级） | AB44: 刘新峥 | AE44: 刘新峥 | AF44: 跟进中 | AG44: 刘新峥
A45: 46112 | B45: 2024-12-30 16:11:54 | C45: XM-2024123018563 | D45: 甬金衢上高速（衢州段） | F45: ，项目主线全长122.361km（其中金华段8.065km，衢州段114.296km）。本项目概算总投资2934431万元，其中建安费1762302万元。隧道9536.5米/12 座（其中长隧道6463m/4座，中隧道1514.5m/2座，短隧道1389m/4座，连拱隧道170m/2座）， 合计分为5个标段，其中3标交工宏图、5标交工大桥有三臂凿岩台车需求。 | G45: 隧道总长9184.5米/12座 | H45: 公路-4 | I45: 特种装备事业部 | J45: 华东区域 | L45: 浙江 | M45: 305.8300000000 | N45: 浙江省交通投资集团有限公司 | O45: 浙江省数智交院 | Q45: ZYS113-1-(/); | R45: 2026-12-31 | S45: CNY 5,000,000.000 | T45: 刘新峥 | W45: 前期与设计院、业主沟通，设计及招标中没有要求智能化机械施工，其要求的施工设备费用需投标人包含在投标综合单价中。3月24日已开标；3标隧道两座（左2450米/右2640米，左495/右472米）中标单位为交工宏图，中标价18.2亿元；5标隧道两座（左495/右472，左1513/右1577）中标单位为交工集团，中标价22.5亿元；同事业部郑松拜访业主建设指挥部，指挥部目前对智能型设备并无太大兴趣。已拜访浙江交工宏途3标（设备由劳务队自带）、交工大桥5标（设备由劳务队自带）；目前已对接劳务队老板，队伍自有设备无设备缺口； | X45: 甬金衢上高速7-9标，招标文件预公示，其中7标长隧道1座（1034米）要求1台全电脑2臂及以上凿岩台车；8标长隧道1座（1331米）要求1台全电脑2臂及以上凿岩台车；9标无隧道。4月7日开标 | Y45: 设计联络 | Z45: 核心问题：业主目前未强制要求智能化配置，且3标交工宏途及5标交工大桥已明确将设备分包至私人老板； 工作思路：全力跟进甬金衢上衢州段建设指挥部，对接隧道大机配套的具体要求，全力推荐机械化智能化配套施工。 关键点：跟进重心放在建设指挥部及施工队伍身上，争取完成突破。 行动计划：继续跟进业主建设指挥部，争取做智能化陪同施工方案交流，明确该项目机械化配套的增加的具体费用，全力跟进各分包队伍老板，说明后续浙江省重点公路项目均要使用智能型设备的利害，早买早摊销成本。 | AA45: 重点信息（Ⅱ级） | AB45: 刘新峥 | AE45: 刘新峥 | AF45: 跟进中 | AG45: 刘新峥
A46: 46112 | B46: 2025-03-31 11:20:27 | C46: XM-2025033119080 | D46: 绍兴市地铁4号线2标 | F46: 人民东路站～迎宾路站区间、迎宾路站、迎宾路站～独树路站区间总共1站2区间涉及的车站及区间的永久工程；迎宾路站：地下一层为站厅层，地下二层为站台层，站台宽度均为 11m。车站主体基坑长 167.00m，标准段宽 19.7m，端头井宽 24.0m，车站覆土约 3m。标准段坑深约 16.65m，西端头井挖深 18.35m，东端头井挖深18.65m；人民东路站～迎宾路站区间区间长度1500米，迎宾路站～独树路站盾构区间区间长度1980米 | G46: 人民东路站～迎宾路站区间区间长度1500米，迎宾路站～独树路站盾构区间区间长度1980米 | H46: 地铁-5 | I46: 掘进机事业部 | J46: 华东区域 | L46: 浙江 | M46: 4.1000000000 | N46: 绍兴市地铁集团 | P46: 中铁十八局市政公司 | Q46: ZTE6950-2-(/); | R46: 2026-06-30 | S46: CNY 15,000,000.000 | T46: 刘新峥 | W46: 已与客户初步洽谈，该项目为合作中标项目，十八局施工1.5公里拟续租或回购杭州地铁10号线DL912/913；私人老板施工1.9公里区间，预计进场时间27年3月、4月份，设备来源暂未明确（需求时间27年4月、5月）。目前回购价格已初步核算1980万； | X46: 继续对接十八局市政公司，明确其公司具体的批复情况，是否在市面上租赁设备。 | Y46: 商务交流 | Z46: 核心问题：绍兴设备租赁价格过低，均在4000元/米以下，业主对设备品牌无要求。十八局一公司有4台厦工中铁设备，可以满足该项目使用。 工作思路：拜访业主单位工程部，针对4号线有难点项目说明利害，让业主严格把控设备质量，同时拜访客户单位，协助华北区域，在今年尽快完成合同续签。 关键点：说服业主，严格把控设备品牌，不能让施工单位为了低价，不顾工程质量。与十八局市政公司做好沟通，已优惠价格完成912/913两台设备的合同续签。 行动计划：尽快拜访业主工程部；协同华北区域全力争取今年完成合同签订。 | AA46: 重点信息（Ⅱ级） | AB46: 刘新峥 | AE46: 刘新峥 | AF46: 跟进中 | AG46: 刘新峥
A47: 46112 | B47: 2025-07-24 18:23:14 | C47: XM-2025072419941 | D47: 杭淳开高速衢州段 | F47: 衢州段合计分为5个标段，中标单位分别为交工金筑、中交二公局、交工集团（交工大桥）、交工宏途、省建投交建；其中1标包含设隧道 6429.5m/5 座，其中特长隧道 1 座(淳开隧道全长 3217m， TJ01 标段实施 3055m)，长隧道 1 座(阳密隧道 1210.5m)，中隧道 2 座(观音尖隧道 923.5m、富林隧道 837m)，短隧道 1 座(天峰隧道 394.5m)需求1台三臂；3标隧道 5766m/3 座，其中特长隧道 1 座(曹门隧道 3067m)、长隧道 1 座〔（上城隧道全长 1416.5m，TJ03 标段实施 1/2 即 708.25m）、（道沃源遂道全长 2716.5m，TJ03 标段实施 1/2即 1358.25m）〕、中隧道 1 座(中村隧道 632.5m)；需求2台三臂；4标特长隧道 1 座(长苏隧道 4709m)、长隧道 3 座〔北源隧道 1935m，枫坞隧道 2629m，（道沃源遂道全长 2716.5m；需求3台3臂 | G47: 。隧道28241米/16座（其中特长隧道10831米/3 座（淳开隧道全长 3217 米，衢州段3055米，杭州段162米），长隧道14291米/8座，中隧道2393米/3座，短隧道726 米/2 座）。 | H47: 公路-4 | I47: 特种装备事业部 | J47: 华东区域 | L47: 浙江 | M47: 136.0000000000 | N47: 浙高建 | O47: 浙江数智交院 | P47: 交工金筑、交工大桥、交工宏途 | Q47: zys123-1-(/); | R47: 2025-12-31 | S47: CNY 8,000,000.000 | T47: 刘新峥 | W47: 衢州段合计分为5个标段，中标单位分别为交工金筑、中交二公局、交工集团（交工大桥）、交工宏途、省建投交建；其中1标包含设隧道 6429.5m/5 座；其中1/3/4标段有长大隧道使用大机配套施工，并要求各标段单独搭建智能化平台。老板已明确年后确定设备来源 | X47: 逐个拜访队伍老板，对接老板的实际设备需求；完成合同签订 | Y47: 商务交流 | Z47: 1、项目施工招标前，邀请事业部拜访业主指挥部进行技术交流，加深业主对我司品牌的了解度，在招标文件中推介品牌加入我司； 2、施工单位进场后，组织业主各标段总工及事业部在业主指挥部进行大机配套技术交流； 3、组织公司领导拜访指挥部指挥长并邀请其到我司考察； 4、11月份走访各个标段项目部及队伍老板，了解其真实想法并反馈至领导及指挥部； 5、12月1日业主组织三个大机标段分公司副总及我司领导到指挥部进行交流 6/12月24日带业主及大机标段到川藏铁路项目考察 | AA47: 重点信息（Ⅱ级） | AB47: 刘新峥 | AE47: 刘新峥 | AF47: 跟进中 | AG47: 刘新峥
A48: 46112 | B48: 2025-07-30 19:50:03 | C48: XM-2025073019970 | D48: 中铁隆绍兴市城市轨道交通4号线6标 | F48: 站2区间1出入段；区间长分别为784米、895米；出入段长422米 | G48: 18000000 | H48: 地铁-5 | I48: 掘进机事业部 | J48: 华东区域 | L48: 浙江 | M48: 3.6600000000 | N48: 绍兴地铁 | P48: 中铁隆 | Q48: ZTE6950-2-(/); | R48: 2026-06-30 | S48: CNY 18,000,000.000 | T48: 刘新峥 | W48: 已与客户盾构施工负责人电话联系，目前项目前期为土地征迁及管线改迁工作，项目盾构人员暂未进场，已告知西南区域负责人；西南反馈事业部认定中铁隆为私企，我司私企条件苛刻。 | X48: 继续跟进中铁隆盾构负责人王小波，了解其设备需求； | Y48: 设计联络 | Z48: 已电话联系盾构施工负责人，目前该项目其公司负责盾构的人员还未进场，预计进场时间为今年年底，该项目设备需求时间为27年4月份。 | AA48: 一般信息（Ⅲ级） | AB48: 刘新峥 | AE48: 刘新峥 | AF48: 跟进中 | AG48: 刘新峥
A49: 46112 | B49: 2025-07-30 19:55:31 | C49: XM-2025073019971 | D49: 绍兴市城市轨道交通4号线3标 | F49: 世茂天际站～平江路站区间、平江路站～人民东路站区间、人民东路站（含5号线人民东路站）总共1站2区间及平江路站附属结构涉及的车站及区间永久工程 | G49: 世茂天际站～平江路站区间1381米；平江路站～人民东路站盾构区间751米 | H49: 地铁-5 | I49: 掘进机事业部 | J49: 华东区域 | K49: 华中区域 | L49: 浙江 | M49: 7.2100000000 | N49: 绍兴地铁集团有限责任公司 | P49: 十五局城轨公司 | Q49: ZTE6950-1-(/); | R49: 2026-06-30 | S49: CNY 2,000,000.000 | T49: 刘新峥 | W49: 十五局城轨公司自有6台6.7米设备目前初步计划使用自有闲置设备DZ1001/DZ1002;基本明确使用自有设备。 | X49: 跟进其具体进场时间，明确其是否需要架立调试。 | Y49: 设计联络 | Z49: 已拜访项目经理，了解该项目初步计划27年2-3月份设备进场。 | AA49: 一般信息（Ⅲ级） | AB49: 刘新峥 | AE49: 刘新峥 | AF49: 跟进中 | AG49: 刘新峥
A50: 46112 | B50: 2025-07-30 20:00:43 | C50: XM-2025073019972 | D50: 绍兴市城市轨道交通4号线8标 | F50: 黄酒小镇站～东浦站区间（含黄酒小镇站盾构接收端土建改造）、东浦站、东浦站～大树江站区间（含区间拔桩）、大树江站总共2站2区间涉及的车站及区间永久工程 | G50: 黄酒小镇站~东浦站区间813米；东浦站~大树江站区间747米 | H50: 地铁-5 | I50: 掘进机事业部 | J50: 华东区域 | K50: 西南区域 | L50: 浙江 | M50: 5.1900000000 | N50: 绍兴地铁集团有限责任公司 | P50: 水电七局轨道公司 | Q50: ZTE6950-2-(/); | R50: 2026-06-30 | S50: CNY 15,600,000.000 | T50: 刘新峥 | U50: 曾彬 | W50: 我司初步向水电七局初步上报的设备方案为DL912/913,由于投标时承诺使用新机，目前客户还在与业主单位沟通新机问题，客户预算3000万。客户初步反馈可能会加快进度在26年6月份进场。其自有两台装备泥水6.7米设备1288/1289正在闲置; | X50: 1、继续对接项目经理夏莹，了解其与绍兴地铁的谈判情况，是否允许其使用准新机。 | Y50: 商务交流 | Z50: 拜访水电七局项目经理，了解项目与业主的谈判情况，配合西南区域一同跟进。 | AA50: 重点信息（Ⅱ级） | AB50: 刘新峥 | AE50: 刘新峥 | AF50: 跟进中 | AG50: 刘新峥
A51: 46112 | B51: 2025-09-01 08:11:13 | C51: XM-2025090120220 | D51: 诸暨至嵊州高速公路 | F51: 项目主线全长约65.3公里，其中诸暨段25.5公里，嵊州段39.8公里，设计时速100公里/小时，采用双向六车道高速公路标准（路基宽度33.5米）。起点位于诸暨市街亭枢纽附近，顺接绍诸高速延伸线；终点为嵊州市三界枢纽，预留向东延伸接口。控制性工程包括穿越诸暨 - 嵊州交界香榧公园的特长隧道群（含竹溪特长隧道，单洞长度超5300米），以及跨谢家水库特大桥（2408米）、樱枝山一号高墩大桥（墩高超80米）。 | G51: 隧道13座总长27087.5米，含2座特长隧道（总长10240米） | H51: 公路-4 | I51: 特种装备事业部 | J51: 华东区域 | L51: 浙江 | M51: 183.0000000000 | N51: 绍兴市诸嵊高速公路有限公司 | O51: 浙江省数智交院 | Q51: ZYS123-1-(/); | R51: 2026-12-30 | S51: CNY 8,000,000.000 | T51: 刘新峥 | W51: 项目在5月7日完成设计招标工作，由浙江数智交院科技股份有限公司中标 | X51: 拜访业主单位 及设计院了解项目对大机配套的要求； | Y51: 定测及初步设计阶段 | Z51: 拜访浙江省数智交院，该项目目前正在初步设计阶段，还未明确是否有要求部分隧道采用大机施工;; | AA51: 重点信息（Ⅱ级） | AB51: 刘新峥 | AE51: 刘新峥 | AF51: 跟进中 | AG51: 刘新峥
A52: 46111 | B52: 2026-02-04 15:14:30 | C52: XM-2026020421410 | D52: 华能霞浦核电项目排水隧道 | F52: 1、福建霞浦核电厂址隶属于宁德市霞浦县长春镇长门村，共3条隧洞，均采用盾构法施工。一期排水隧道，直径8.1m，长度1.88km；二期排水隧洞，直径8.1m，长度3.4km。三期排水隧洞，直径8.1m，长度4.2km。 2、一期目前处于初步设计阶段，预计2026年第一季度开工。 3、业主：华能霞浦核电有限公司； 4、设计院：中交四航院； 5、总包方：中核工业。分包工程均在华能电子商务平台上招标，投标单位要同时入围了中国核工业及中国华能供应商库。 设备需求：3台ZTS9100。 | G52: 一期排水隧道，直径8.1m，长度1.88km；二期排水隧洞，直径8.1m，长度3.4km。三期排水隧洞，直径8.1m，长度4.2km。 | H52: 电力-14 | I52: 掘进机事业部 | J52: 华东区域 | L52: 福建 | M52: 456.0000000000 | N52: 华能霞浦核电有限公司 | O52: 中交四航院 | P52: 总包方：中核工业 | Q52: ZTS9100-1-(/); | R52: 2026-07-31 | S52: CNY 150,000,000.000 | T52: 周斌 | W52: 1、2024年9月份开始跟进，建立项目台账； 2、2025年12月份，盾构机始发井确定采用竖井掘进机施工。 3、霞浦核电站一期工程排水隧道计划在2026年3月份招标。 4、与中铁15局福宁经营部对接，此项目盾构机始发井采用竖井掘进机施工将会作为招标条件，2026-2-13 5、一期排水隧洞原计划3月底招标，现推迟至6月份招标。2026-3-15 6、与中铁15局福建经营部一同拜访了业主单位（中国华能），交流了竖井掘进机施工技术。 2026-3-30 | X52: 1、配合系统内工程局完成项目承揽，中铁14局、15局、18局、19局跟进较为积极。 | Y52: 施工图设计阶段 | Z52: 1、我设计院对接盾构机选型、始发井采用竖井掘进机施工方案。 | AA52: 一般信息（Ⅲ级） | AB52: 周斌 | AE52: 周斌 | AF52: 跟进中 | AG52: 周斌
A53: 46111 | B53: 2025-11-03 21:12:01 | C53: XM-2025110320608 | D53: 将乐百祥矿业长距离皮带机项目 | F53: 项目名称：将乐百祥矿业有限公司际下矿段方解石矿建设项目 1、业主:将乐百祥矿业有限公司，民营企业，成立于2019年，位于福建省将乐县高唐镇楼杉村，专注于非金属矿开采与销售。 2、矿区至加工厂距离24km，其中约10km为山路，道路交通条件差，计划将修建隧道，采用皮带机运输。计划2年内完成隧道与皮带机建设。目前十四局集团公司华东经营部牵头对接业主，计划向业主推荐EPC模式，由十四局牵头，联合铁一院，我司配合提供设备技术支持。 | G53: 计划将修建隧道，采用皮带机运输，10公里隧道， | H53: 非煤矿山-11 | I53: 矿山装备事业部 | J53: 华东区域 | L53: 福建 | M53: 3.3680000000 | N53: 将乐百祥矿业长距离皮带机项目 | Q53: 800-1-(2027-12-30); | R53: 2026-08-31 | S53: CNY 60,000,000.000 | T53: 周斌 | W53: 2、2024 年，将乐县自然资源局顺利完成了百祥矿业方解石矿的探矿权转采矿权工作。2025 年 7 月 7 日， 2、三明市生态环境局受理了该项目的环境影响评价文件。截至 2025 年 7 月，项目的环境影响报告书已基本完成编制工作， 3、且建设单位已同步完成该项目环境影响公众参与说明编制工作，并进行了公示。 4、我司给铁一院提供了皮带机方案、基本参数及尺寸。2025-11-13 5、与中铁14局，铁一院催化项目EPC招标，招标基本资料已准备，代理商已确认，计划在本周挂网招标公告，在12月20日前完成招标工作。2025-11-27 6、施工招标于12月1日已挂网，EPC模式，2025-12-3 7、中铁14局、铁一院联合体中标，跟进EPC合同签订进展，2025-12-29 8、与中铁14局、铁一院的拜访了业主单位方岩集团，此项目要求在2027年年底隧道贯通，隧道区间有10公里，5米宽城门洞型，采用钻爆发施工，一个支洞，2026-1-16 9、此项目施工合同暂未签订，铁一院的设计工作已启动。2026-2-13 10、拜访了中铁14局福建经营部，此项目目前处于资金筹备中，待资金基本确定后立即启动，2026-3-23 | X53: 对接项目进展，跟进开标结果 | Y53: 设计联络 | Z53: 1、024 年，将乐县自然资源局顺利完成了百祥矿业方解石矿的探矿权转采矿权工作。 2025 年 7 月 7 日，三明市生态环境局受理了该项目的环境影响评价文件。截至 2025 年 7 月，项目的环境影响报告书已基本完成编制工作，且建设单位已同步完成该项目环境影响公众参与说明编制工作，并进行了公示。 | AA53: 一般信息（Ⅲ级） | AB53: 周斌 | AE53: 周斌 | AF53: 跟进中 | AG53: 周斌
A54: 46111 | B54: 2025-09-21 11:52:15 | C54: XM-2025092120374 | D54: 中铁十七局沈海线漳诏高速扩容工程A9标 | F54: 沈海线漳诏高速扩容工程，共计13个标段，中铁17局中的中标的A9标中，大臣山隧道2339m作为本工程隧道全机械施工试验工点，业主为机械化施工提供500万费用。 | G54: 2.3公里隧道 | H54: 公路-4 | I54: 特种装备事业部 | J54: 华东区域 | L54: 福建 | M54: 169.7400000000 | N54: 福建省漳州高速公路有限公司（漳州漳诏高速扩建工程有限公司）） | O54: 福建省交通规划设计院 | P54: 中铁十七局第六工程有限公司 | Q54: MT141-2-(/);ZYS113-2-(/); | R54: 2026-05-31 | S54: CNY 50,000,000.000 | T54: 周斌 | W54: 1、2024 年 7 月，福建省发展和改革委员会批复了沈海线漳州龙海至诏安段（龙海北溪头至诏安闽粤界）扩容工程可行性研究报告。 2、2025 年 3 月，福建省发展和改革委员会同意调整该项目可行性研究报告中资本金出资来源。 3、2025 年 6 月 30 日，项目施工图设计正式获得福建省交通运输厅批复，为下阶段开展路基土建施工、监理及检测招标，实现 4、2025 年 9 月份开工建设迈出坚实一步。 5、2025 年 7 月，福建省工程领域招投标在线监管平台发布了该项目路基土建工程施工招标公告。 6、2025 年 9 月，该项目获自然资源部批准先行用地 30.6536 公顷，是全省首个参建单位还未正式进场就先取得用地批复的高速公路建设项目。 7、中铁17局中标9标段，隧道区间2.3公里，为大机配套试验段。 8、业主要求采用全电脑设备，我司提供了凿岩台车、拱架台车、钻锚注一体机、湿喷台车报价。 9、中铁17局项目部回复，首选劳务队自带，次之为租赁，最后才是采购。2025-11-13 10、拜访了中铁17局6公司设备部龙部长，他们提出大机配套有回购的采购要求，咨询了特装事业部，2年后的回购残值不高于15%.，2025-11-25 11、业主要求承建方提供全电脑凿岩台车、拱架台车、钻锚注一体机；中铁17局6公司中标，此项目设备将由劳务队自带，他们将要求劳务队使用铁建重工的全电脑三臂凿岩台车。12-29 12、计划于2026年1月20日与中铁17局6公司组织特装产品技术交流会。2026-1-16 13、提供设备正式报价，先需求1台全电脑三臂凿岩台车，1台全电脑二臂凿岩台车，1台钻锚注一体机。2026-1-31 5、需求两台小三臂凿岩台车，提供技术参数表，提供劳务招标凿岩台车技术要求，2025-2-13 6、拜访中铁17局6公司设备物资部，由劳务队采购，还未最终确定劳务队，2026-3-23 | X54: 跟进中铁17局6公司设备需求情况。 | Y54: 设计联络 | Z54: 9标为机械化施工试验标段。 | AA54: 一般信息（Ⅲ级） | AB54: 周斌 | AE54: 周斌 | AF54: 跟进中 | AG54: 周斌
A55: 46111 | B55: 2025-11-03 20:57:04 | C55: XM-2025110320607 | D55: 中铁十七局潮州至南昌高速福建三明段A7标 | F55: 1、项目全长约96.006公里，建安投资约96.42亿元。 2、计划11月7日开标，分8个标，A7标有机械化施工要求。A7 标段的大坪隧道进口端作为隧道全机械施工试验工点，经费500万。 | G55: A7 标段的大坪隧道进口端作为隧道全机械施工试验工点，经费500万。 | H55: 公路-4 | I55: 特种装备事业部 | J55: 华东区域 | L55: 福建 | M55: 99.6000000000 | N55: 三明昌潮高速公路有限责任公司 | O55: 中交第一公路勘察设计研究院 | Q55: ZYS113-2-(/);MT141-2-(/); | R55: 2026-07-31 | S55: CNY 50,000,000.000 | T55: 周斌 | W55: 1、对接中铁17局6公司设备部龙部长，他们证在招劳务标，首选劳务队自带，如他们采购，必须有回购的采购要求，咨询了特装事业部，2年后的回购残值不高于15%。12-8 2、中铁17局已明确由劳务队带设备进场施工，劳务招标计划在1月份进行。12-29 3、计划于2026年1月20日与中铁17局6公司组织特装产品技术交流会。2026-1-16 4、待劳务招标，由劳务队带设备进场施工，2026-2-13 5、与工程局在项目部做了隧道施工大机配套技术交流，需求两套。2026-3-30 | X55: 跟进项目设备需求进展。 | Y55: 设计联络 | Z55: 1、开标日期由10月30日推迟至11月7日，系统内中铁12局、大桥局、14局、16局、17局、22局跟进较为积极。 2、计划11月7日开标，分8个标，A7标有机械化施工要求。A7 标段的大坪隧道进口端作为隧道全机械施工试验工点，经费500万。 3、中铁17局6公司中标A7标，有隧道施工设备需求，招标公式中，2025-11-13 4、拜访了中铁17局6公司设备部龙部长，他们提出大机配套有回购的采购要求，咨询了特装事业部，2年后的回购残值不高于15%.，2025-11-25 | AA55: 一般信息（Ⅲ级） | AB55: 周斌 | AE55: 周斌 | AF55: 跟进中 | AG55: 周斌
A56: 46111 | B56: 2025-03-25 21:36:01 | C56: XM-2025032519021 | D56: 厦门九龙江北溪引水左干渠提升改造工程 | F56: 1、九龙江北溪引水左干渠提升改造工程，总投资182800万元 2、龙屿节制闸至过芸溪段：新建输水通道总长约 5.43 千米，其中海沧水厂上游段隧洞长 3.62 千米，海沧水厂下游段隧洞长 1.72 千米，输水箱涵长 0.09 千米。 -深青溪至杏林取水口段：新建输水通道总长约 5.44 千米，其中隧洞长 4.58 千米，输水箱涵长 0.86 千米。 3、隧道计划采用管片外径6.2米盾构机施工，主要穿越的地层有残积砂质粘性土、全风化花岗岩、散体状强风化花岗岩、碎裂状强风化花岗岩、中风化花岗岩。 | G56: 预计采用6.2米管片外径的盾构机，总隧道总长约10公里。 | H56: 水利水电-0 | I56: 掘进机事业部 | J56: 华东区域 | L56: 福建 | M56: 18.0000000000 | N56: 厦门市政原水运营公司 | O56: 上海市政设计院 | Q56: ZTE6430-1-(2026-03-31);ZTE5630-2-(/); | R56: 2026-08-31 | S56: CNY 10,000,000.000 | T56: 周斌 | W56: 1、对接设计院，拿到了项目可研资料。 2、预计在2025年7月份招水闸标。 3、对接上海市政院，根据业主要求，涉铁区间单独拎出来，则盾构段分为三个区间了，需求2台ZTE6480，1台ZTE5580，预计在10月份招盾构段标，2025-6-27 4、九龙江左干渠盾构标分两个，一个5亿多，一个4亿，预计在11月20日招标。资质设一级水利，一级市政，业绩要求：盾构长度不少于3公里。2025-10-13 5、因涉铁事宜处理耽误，盾构段招标预计推迟至2026年4月份，2026-2-13 6、此项目为专项债项目，资金情况预计在3月底能明确下来，招标预计在6月份左右进行，2026-3-30 | X56: 1、对接业主，跟进项目进展； 2、配合系统内单位跟进。 | Y56: 施工图设计阶段 | Z56: 核心问题：系统内单位能否中标； 工作思路：积极跟进项目进展，业主计划在6月份招标，协助系统内单位承揽项目； 关键点：1台6.2米管片外径盾构机，此型号盾构机闲置设备偏多，我司租赁方案是否具备竞争优势；5.3米管片外径盾构机是否具备价格优势。 行动计划：积极跟进项目进展，落实开标时间，配合系统内单位投标。 | AA56: 一般信息（Ⅲ级） | AB56: 周斌 | AE56: 周斌 | AF56: 跟进中 | AG56: 周斌
A57: 46111 | B57: 2024-03-18 21:50:49 | C57: XM-2024031816424 | D57: 福建“一库三线”项目 | F57: 1、闽江口城市水资源配置提质增效（一库三线）工程，该工程向福州主城区、滨海新城、莆田等地供水，总体布局为“一库三线”，即在大樟溪新建龙湘大型水库；新建福州主城区、滨海新城及莆田3条输水线路，线路总长约166.5公里，其中新建约76.5公里。 2、初步投资匡算约192亿元。 | G57: 8.6米盾构机一台，穿乌龙江，区间长度约2公里；4.5米TBM一台，莆田境内，区间长度约17.7公里；1.8~2米顶管机十来台 | H57: 水利水电-0 | I57: 掘进机事业部 | J57: 华东区域 | L57: 福建 | M57: 192.0000000000 | N57: 福州水务集团有限公司、莆田市水务集团有限公司 | O57: 福州城建设计研究院有限公司、福建省水利水电勘测设计研究院有限公司 | P57: 待定 | Q57: ZTP3700-2-(/);ZTS8300-1-(/);ZTT4500-1-(/); | R57: 2027-12-01 | S57: CNY 10,000,000.000 | T57: 周斌 | W57: 1、拜访福州市水利投资集团有限公司总工，根据你项目进展，福建水投为一库三线中的福州线和滨海线业主单位； 2、此项目需要水利部批准，手续变繁琐了，预计在2025年年底启动招标工作。 3、2025年3月14日完成规划报批评审工作，预计在2026年年中施工招标。 4、可行性研究报告通过初审：2025年2月24日至25日。 5、2025年3月24日，福州市水利局召开了“一库三线”工程2025年第2次前期工作协调推进会议。 6、此项目已完成省水利厅的可研报批，计划9月前完成太湖流域可研报批，争取在年底前完成水利部可研报批，2025-6-23 7、与中铁18局隧道公司拜访省水电院。2025-7-22 8、拜访了省水电院，可研初稿编制中，2025-8-11 9、可研审批初稿已提交太湖流域审批，2025-8-21 10、拜访设计院，福建院，暂时无进展 2025-5-2 11、可研初稿已过省水投评审，计划下周报送太湖流域审批。2025-9-21 12、我司给设计院提供了泥水盾构机方案，我司设计负责人谢蛟，2025-10-30 13、福州段穿乌龙江盾构机有计划改顶盾施工。2025-11-27 14、项目可研被退回，要求根据水利部最新的投资要求重新提报预可研资料，项目预计推迟至2027年年中才能启动招标工作。2025-12-8 14、本周无进展，2026-3-30 | X57: 持续跟进。 | Y57: 项目立项阶段（预可研，初测及可研，环评） | Z57: 核心问题：中铁建是否能拿到福州段盾构机穿江标段，中铁装备有两台8.6米泥水盾构机在福州存放（福州滨海快线退下来的，在闽侯乾达重工存放），工程标什么时候开；莆田段TBM方案是否能落地。 工作思路：积极跟进落实项目进展，与系统内单位分享配合项目进展信息，配合各单位跟进，预计2026年第二季度开标。 关键点：8.6米泥水盾构机，我司无相关设备，中铁装备、中交天和有设备，可否使用土压改造。 行动计划：拜访设计院、业主单位，跟进项目进展，积极配合系统内单位，协助项目承揽。 | AA57: 重点信息（Ⅱ级） | AB57: 周斌 | AE57: 周斌 | AF57: 跟进中 | AG57: 周斌
A58: 46111 | B58: 2024-08-17 22:47:47 | C58: XM-2024081717582 | D58: 福州地铁第3轮规划（6号线西延线） | F58: 福州市轨道交通6号线西延线工程起于洪塘站，终于潘墩站（不含）。线路全长约13.6km，共设车站9座，平均站间距1.486km；全线均为地下敷设。投资总额约135.08亿元 2、业主组成： 业主单位：福州地铁集团， 设计单位：福州地铁轨道交通设计院 | G58: 线路全长约13.6km，共设车站9座，平均站间距1.486km；全线均为地下敷设。 | H58: 地铁-5 | I58: 掘进机事业部 | J58: 华东区域 | L58: 福建 | M58: 135.0800000000 | N58: 福州地铁集团 | O58: 福州地铁轨道交通设计院 | P58: 待定 | Q58: ZTE6410-6-(/); | R58: 2027-03-30 | S58: CNY 30,000,000.000 | T58: 周斌 | W58: 1、2023年12月份国家发改委批准了福州地铁第三轮规划； 2、2024年5月7日~9日组织了福州地铁第三轮规划评审； 3、2024年8月24日，我司董事长拜访福州地铁集团董事长。 4、2024年9月13日，我司与福州地铁集团组织盾构机新技术交流会。 5、2024年9月底，施工用地审批有序已批准。 6、预计在2025年9月份招标。 7、福州地铁第3轮规划（6号线西延线、3号线、S1线）建规报批被退回来了，就在五一节后这几天。听说这次是全国性的，没有开工建设的项目都被退回来了。发改委要修编，听说今年年底能出新的规范，要待新的规范下来后再重新申报。所以福州地铁第3轮最快也要到明年年底才能启动，2025-5-23 8、福州第3轮规划报批被退回，预计2026年年初能重新提报，争取在2026年年底能批复。2025-6-14 9、项目无新进展。2025-8-21 10、项目无新进展。2025-10-21 11、福州第三轮规划因在运营的地铁上座率不够，被再次退回了，现申请取消。如后续再启动，重新申报。2025-12-23 12、本周无新进展，2026-3-30 | X58: 1、对接福轨院，了解项目设计进展； 2、对接福州地铁集团，跟进项目施工招标进展； 3、对接福州地铁实业，落实盾构机转租、转售。 | Y58: 可行性研究报告获批 | Z58: 核心问题：是否能销售、租赁盾构机，采用什么模式。 工作思路：积极对接福州地铁实业公司，推进盾构机转销、转租。 关键点：与福州地铁实业合作，推进盾构机转销、转租模式，策划新机需求。 行动计划：拜访福州地铁公司相关部门和福轨院，跟进项目进展情况。 | AA58: 重点信息（Ⅱ级） | AB58: 周斌 | AE58: 周斌 | AF58: 跟进中 | AG58: 周斌
A59: 46111 | B59: 2024-08-17 23:30:25 | C59: XM-2024081717583 | D59: 厦门轨道交通3期（9号线二期） | F59: 1、线长18.8km，设站14座，设停车场一座； 2、跨海段采用管片外径11.8米泥水平衡盾构机施工，区间长度2.7公里，需求1台，业主于2024年8月24日组织了盾构机选型评审会。 3、业主单位：铁一院；业主单位：厦门轨道交通 | G59: 18.8km、14站、全地下敷设 | H59: 地铁-5 | I59: 掘进机事业部 | J59: 华东区域 | L59: 福建 | M59: 405.0000000000 | N59: 厦门轨道交通建设集团 | O59: 铁一院 | P59: 铁一院 | Q59: ZTS12400-1-(/); | R59: 2026-10-31 | S59: CNY 100,000,000.000 | T59: 周斌 | W59: 1、拜访业主单位、设计院及中铁建福建经营部，跟进项目进展； 2、项目核准暂未批复，预计在2025年第三季度招标。 3、厦门第3轮规划（9号线2期、5号线、8号线）建规报批被退回来了，就在五一节后这几天。听说这次是全国性的，没有开工建设的项目都被退回来了。发改委要修编，听说今年年底能出新的规范，要待新的规范下来后再重新申报。所以厦门地铁第3轮最快也要到明年年底才能启动，2025-5-23 4、厦门第三轮申请被接收，9号线二期预计在2026年第二季度招标，跨海段2.7公里采用11.8米管片外径泥水盾构机施工。配合系统内单位开展土建施工承揽，重点放在跨海11.8米泥水盾构机。2025-12-29 5、暂无新进展，2026-3-30 | X59: 与业主单位、设计院紧密联系 | Y59: 项目立项阶段（预可研，初测及可研，环评） | Z59: 核心问题：系统内单位能否中标 工作思路：积极跟进项目进展，业主计划在2025年8月份招标，协助系统内单位承揽项目。 关键点：1台11.8米管片外径泥水盾构，第三轮规划的5号线跨海段是否会选用此型号盾构机，此项目中标单位盾构机是新购还是改造。 行动计划：积极跟进项目进展，落实开标时间，配合系统内单位投标。 | AA59: 重点信息（Ⅱ级） | AB59: 周斌 | AE59: 周斌 | AF59: 跟进中 | AG59: 周斌
A60: 46111 | B60: 2023-06-03 13:55:02 | C60: XM-2023060313944 | D60: 上饶至浦城高速公路（福建段） | F60: 路线规划：起于闽赣交界浦城县盘亭乡界牌村（顺接已通车的江西段），终于官路乡河村村，衔接 G3 京台高速，全长 19.008 公里（较原规划缩短约 10 公里）。 建设标准：双向四车道高速公路，设计时速 100km/h，路基宽度 26 米，桥隧比例 57.7%（桥梁 16 座 / 5937.5 米、隧道 2 座 / 5030 米），设盘亭互通、官路枢纽互通 2 处，浮盖山服务区（兼高速出入口）1 处。 | G60: 上饶至浦城高速公路（福建境内）共有6座隧道，总长度为2500米‌‌。 | H60: 公路-4 | I60: 特种装备事业部 | J60: 华东区域 | L60: 福建 | M60: 30.0000000000 | N60: 南平市高速公路有限责任公司 | O60: 福建省交通规划设计院 | Q60: HZS120-2-(/); | R60: 2026-08-31 | S60: CNY 1,500,000.000 | T60: 周斌 | W60: 1、目前中铁建二十局，十四局，十八局都在接触南平市政府和交投，拟引进工程投资平台公司来筹集资金。根据2025年3月赣闽专项会议决议，上浦高速福建段已成立专项项目公司，正推进工程可行性研究阶段筹备工作，计划在"十五五"规划期初期开工建设。2026-1-16 2、暂无新进展 2026-3-30 | X60: 暂缓跟进，保持关注项目进展。 | Y60: 可行性研究报告获批 | Z60: 目前中铁建二十局，十四局，十八局都在接触南平市政府和交投，拟引进工程投资平台公司来筹集资金。 | AA60: 重点信息（Ⅱ级） | AB60: 陆顺 | AE60: 陆顺 | AF60: 跟进中 | AG60: 周斌
A61: 46111 | B61: 2023-06-03 14:00:36 | C61: XM-2023060313939 | D61: 沈海高速福厦段二期扩容工程 | F61: 主线设有桥梁71007.5米/37座，隧道长度为1000米/2座（扩建后）。莆炎高速与莆永高速联络线部分，桥梁长度为8971米/9座，隧道长度为2020米/1座。 | G61: 高架路面扩宽为主，隧道扩建较少 | H61: 公路-4 | I61: 特种装备事业部 | J61: 华东区域 | L61: 福建 | M61: 120.0000000000 | N61: 福建省高速公路集团有限公司 | O61: 福建省交通规划设计院 | Q61: HZS120-2-(/); | R61: 2026-10-31 | S61: CNY 3,000,000.000 | T61: 周斌 | W61: 1、2025年5月15日在北京召开工可修编方案咨询评估，围绕交通量分析预测、技术标准拟定、建设方案设计、交通组织模式规划及财务分析等核心内容展开深度研讨，其中很明确表示，要进行探索“上客下混”通行模式，即上层高速为客车通道，而下层为客车与货车混合通道。预计2026年启动建设。2026-1-16 2、此项目列入了省重点启动项目，2026-3-30 | X61: 项目推进缓慢，暂缓跟进。 | Y61: 定测及初步设计阶段 | Z61: 已初步对接设计单位了解项目实时进展。 | AA61: 重点信息（Ⅱ级） | AB61: 陆顺 | AE61: 陆顺 | AF61: 跟进中 | AG61: 周斌
A62: 46111 | B62: 2023-06-04 20:49:20 | C62: XM-2023060413979 | D62: 福州地铁3轮规划（S1线祥谦至福清） | F62: 1、在福州主城区范围内共设置福州南站、祥谦站、中央公园站、汽车城站、东台工业园站5个站点； 2、在福清内主要沿福百路走向，设置清繁大道站、清荣大道站、清昌大道站、创业大道站、福清站5个站点。线路长约40km，S1线将与F1线在祥谦站互联互通，可以实现福清市区、福州南站与长乐机场的直连。 | G62: 福州市内：其中两座长大隧道（1km、5.8km），1km隧道暂定为矿山法施工。5.8km隧道（穿山、硬岩）计划采用TBM施工。福清市内：其中4.2km（1km软土（未完全探明），2.2km（穿山硬岩），1km穿越既有火车站场（考虑沉降）），计划采用双模或利用风井进入土压、TBM进行开挖 | H62: 地铁-5 | I62: 掘进机事业部 | J62: 华东区域 | L62: 福建 | M62: 160.0000000000 | N62: 福州地铁集团 | O62: 福州轨道交通设计院 | Q62: 土压平衡盾构机/单护盾TBM-5-(/); | R62: 2026-12-31 | S62: CNY 20,000,000.000 | T62: 周斌 | W62: 1、2024年5月7~9号福州地铁召开第3轮规划建规报批 2、2024年10月份土地施工用地已批复。 3、第3轮规划报批被退回，预计2026年年初能重新提报，争取在2026年年底能批复 2025-6-5 4、此项目暂无进展。2025-9-8 5、无新进展，持续跟进，2026-3-13 | X62: 持续跟进。 | Y62: 项目立项阶段（预可研，初测及可研，环评） | Z62: 核心问题：是否能销售、租赁盾构机，采用什么模式。 工作思路：积极对接福州地铁实业公司，推进盾构机转销、转租。 关键点：与福州地铁实业合作，推进盾构机转销、转租模式，策划新机需求。 行动计划：拜访福州地铁公司相关部门和福轨院，跟进项目进展情况。 | AA62: 重点信息（Ⅱ级） | AB62: 周斌 | AE62: 周斌 | AF62: 跟进中 | AG62: 周斌
A63: 46111 | B63: 2021-03-22 16:17:26 | C63: XM-202103225455 | D63: 沈海联络线泉（州）梅（州）高速公路泉州段 | F63: 1、泉梅高速（泉州段）：起于沈海高速黄塘互通，向西经洛江区、南安市，于码头镇铺前村西侧设铺前枢纽汇入现状泉南高速。将原泉南高速由6车道双侧拓宽至8车道，止于永春互通。 2、路线全长58.243Km，其中新建里程37.251Km，原位扩容里程20.992Km。隧道4048米/4座，隧道占路线里程7.07%，工程投资估算为95.1334亿元。 3、业主单位：泉州市泉三高速公路投资有限责任公司 | G63: 隧道4048米/4座 | H63: 公路-4 | I63: 隧道装备研发运营中心 | J63: 华东区域 | K63: 无部门 | L63: 福建 | M63: 95.1334000000 | N63: 泉州市泉三高速公路投资有限责任公司 | O63: 待定 | P63: 待定 | R63: 2026-08-31 | S63: CNY 100,000,000.000 | T63: 周斌 | V63: 项目立项阶段（预可研，初测及可研，环评） | W63: 1、项目处于前期研究阶段。拜访福建交规院了解相关情况。 2、目前设计院还在做前期设计勘察，项目可研已通过。 3、福建省交通运输厅 2025 年 4 月 30 日发布的信息，沈海联络线泉（州）梅（州）高速公路泉州段已完成 “工可” 审查， 4、泉州市正在按要求优化方案和修编 “工可”。根据泉州公布的 2025 年重点项目安排，泉梅高速预计建设周期为 2026-2029 年。 5、项目无新进展。2025-8-21 6、交通运输部出具关于 G1532 泉梅高速泉州段工程建设资金安排意见，拟安排中央交通运输领域重点项目资金 14.96 亿元，标志着该项目前期工作取得重大突破， 2025年9月8日。 7、暂无新进展，2025-11-13 8、业主回复预计在明年第二季度招标，2025-12-8 9、本周无新进展，2026-1-16 10、2026 年福建省与泉州市均将该项目列入年度拟开工重点高速，明确年内启动建设，工期约 4 年，预计 2029 年建成通车 2026-3-23 | X63: 继续跟踪 | Y63: 定测及初步设计阶段 | Z63: 核心问题：项目模式确定、开工时间确定。 工作思路：依靠系统内单位运作，关注招标中标情况。 关键点：摸清中标后的各单位搅拌站需求和劳务情况。 行动计划：拜访系统内单位和福建省高速指挥部，了解情况。2025年下半年预计施工招标，搅拌站需求 | AA63: 重点信息（Ⅱ级） | AB63: 陆顺 | AE63: 接口专用帐号 | AF63: 跟进中 | AG63: 周斌
A64: 46111 | B64: 2021-07-10 14:16:49 | C64: XM-202107107455 | D64: 闽西南水资源配置工程 | F64: 1、闽西南引水工程 1.1、工程总体布局为 “两库两闸三线”，总投资 342 亿元。“两库” 分别是漳平浙溪大型水库、华安罗溪中型水库；“两闸” 为九龙江北溪水闸和西溪桥闸；“三线” 为棉花滩、漳州和厦泉等 3 条输水线路。其中泉厦支线，棉花滩支线隧洞会用到TBM施工，TBM隧洞约100公里。预计在2026年下半年启动施工招标工作。 1.2项目名称：闽西南水资源配置工程。 相关单位：业主单位：省水投集团；设计单位：省水利水电设计院。 建设地点：龙岩市、漳州市、厦门市、泉州市。 建设内容：工程由新建水库和输水工程组成。 设备需求：预计采用10台5至7米硬岩掘进机，5台3米~5米硬岩掘进机。 | G64: 初步规划采用3~8米洞径，2、3、4类围岩，100到200兆帕，地下水丰富，TBM施工隧洞总长约150公里。 | H64: 水利水电 | I64: 掘进机研发运营中心 | J64: 华东区域 | L64: 福建 | M64: 342.0000000000 | N64: 福建水投 | O64: 福建省水利水电勘察设计院 | P64: 待定 | Q64: 3~8米-15-(2027-12-01); | R64: 2027-09-01 | S64: CNY 150,000,000.000 | T64: 周斌 | W64: 1、我司已与福建水电院完成两轮TBM技术交流，及时跟进规划进展； 2、福建与广东已解决水资源争执已解决，项目重新启动。 3、2025年3月19日，省水利厅党组成员、副厅长余德贵召开闽西南水资源配置工程前期工作推进视频会，12月项目可研报告送水利部审查、2026年底项目开工建设 4、2025年3月19日，省水利厅党组成员、副厅长余德贵召开闽西南水资源配置工程前期工作推进视频会。会议通报了分水方案、用水需求、规划环评依据等进展情况，并明确了工作目标，即围绕今年12月项目可研报告送水利部审查、2026年底项目开工建设的目标，加快工程总体布局和规模论证、规划环评及可研报告前置专题报告编审工作，尽早完成可研立项。 5、拜访福建省水电设计院，闽西南新增了漳浦-云霄输水隧道，约51公里，采用3台TBM施工。此项目争取在年底前完成省水利厅审批，在明年3月份完成太湖流域报批，在2026年年中完成水利部项可研报批。2025-6-14 6、陪同中铁19局拜访省水电设计院。 7、陪同中铁18局隧道公司拜访省水电设计院。 8、工程总体布局为 “两库两闸三线”，总投资 342 亿元。“两库” 分别是漳平浙溪大型水库、华安罗溪中型水库；“两闸” 为九龙江北溪水闸和西溪桥闸；“三线” 为棉花滩、漳州和厦泉等 3 条输水线路。其中泉厦支线，棉花滩支线隧洞会用到TBM施工，TBM隧洞约100公里。预计在2026年年中完成水利部项可研报批，在2027年年初启动施工招标工作。 业主单位：省水投集团；设计单位：省水利水电设计院。 设备需求：预计采用5～8台5至7米硬岩掘进机，3台3米硬岩掘进机。2025-8-11 9、拜访设计单位，漳州漳浦支线，6公里，有计划从钻爆法改TBM施工，开挖直径5米，2021-8-15 10、本周设计院组织了闽西南引水工程可研二次专家评审，与我司相关的为TBM隧道未提出异议，2025-9-17 11、预计采用10台5至7米硬岩掘进机，5台3米~5米硬岩掘进机，2025-10-30 12、拜访省水电设计院，可研报批被退回，资料需根据水利部最新要求重新编制，从预可研开始重走报批手续，争取在2016年年底完成科研报批。2025-12-23 13、项目规划建议书审批中，2026-3-30 | X64: 拜访福建省水利水电设计院，跟进项目进展，预计2025年12月可研报批。 | Y64: 项目立项阶段（预可研，初测及可研，环评） | Z64: 核心问题： 什么时候能重新启动，采用多少台TBM及钻爆法施工设备； 工作思路： 积极对接福建省水利水电设计院，跟进项目进展，配合系统内单位承揽项目； 关键点： 项目是否能重新启动，采用TBM施工及钻爆法施工工程量， 行动计划： 积极落实项目进展，配合设计院完成项目隧道设计工作。 | AA64: 重点信息（Ⅱ级） | AB64: 周斌 | AE64: 周斌 | AF64: 跟进中 | AG64: 周斌
A65: 46111 | B65: 2021-03-22 16:17:25 | C65: XM-202103225449 | D65: 厦漳泉R1线 | F65: 1、厦漳泉 R1 线项目总投资最终确定为约695.7 亿元。该线路全长 175.04 公里，途经泉州、厦门、漳州三地。 2、业主单位，厦门：厦门地铁集团，漳州：漳州铁路投资有限公司，泉州：泉州轨道交通集团，总规划设计院是总铁二院。 3、全线正线中桥梁长度 88.278 公里，隧道长度 78.111 公里，结合全长 175.04 公里计算，桥梁占比约 50.4%，隧道占比约 44.6%，剩余约 5% 为路基（路基长度 5.797 公里）。 4、中国铁建股份成立的专班，厦门专班：成员单位中铁十二局、中铁十四局、中铁海峡（中铁22局3公司）；漳州专班：中铁建漳州公司（中铁十二局）、中铁十五局、中铁二十二局、中铁十八局（新增）；泉州专班：中铁建泉州公司（中铁建大桥局），中铁十七局，中铁二十局，中铁十六局（新增）、中铁二十四局（新增）。 | G65: 线路全长约206KM | H65: 轨道交通-12 | I65: 掘进机事业部 | J65: 华东区域 | K65: 无部门 | L65: 福建 | M65: 695.7000000000 | N65: 厦门轨道交通集团有限公司、泉州轨道交通集团有限公司、漳州轨道交通集团有限公司 | O65: 铁二院 | P65: 待定 | Q65: ZTS8300-10-(2026-12-01);ZTS12960-4-(2026-12-01);ZTE8300-29-(2026-12-01); | R65: 2026-09-01 | S65: CNY 200,000,000.000 | T65: 周斌 | V65: 定测及初步设计阶段 | W65: 2025.5.14 集团贺总、韩总、华东区域张总拜访泉州轨道交通集团陈董事长、马总经理。 2025.6.11 拜访厦门轨道合约部惠部长，确认厦门 R1 线无强制使用厦工中铁盾构机要求；厦门先期标 9 月招标，含涠洲湾大桥、大登岛明挖段、4 个盾构井，全线年底前大标段开标，以股份公司名义投标。 2025.6.16 与中铁十二局拜访漳州交发陈总工，漳州拟 3 个大标段招标；同步拜访铁二院漳州分院，获取厦漳泉 R1 线全线可研报批最终稿。 2025.6.27 拜访铁二院泉州院，泉州段年内全线动工，池店 — 东海新区盾构段预计 9 月招标。 中铁建股指成立 R1 线项目专班： 厦门：中铁十二局、十四局、中铁海峡（22 局 3 公司） 漳州：中铁建漳州公司（十二局）、十五局、二十二局、十八局 泉州：中铁建泉州公司（大桥局）、十七局、二十局、十六局、二十四局 2025.7.15 拜访中铁十五局漳州专班；7.24 中铁二十局泉州专班进驻。 泉州先期标 1 个车站预计 8 月开标，剩余土建约 150 亿 10 月招标。 初次拜访漳州铁路投资有限公司林总经理。 2025.8.6 韩总拜访泉州交发，业主不强制指定盾构机品牌。 2025.8.21 泉州先期标（池店车站）、厦门先期标（石井站 — 翔安机场站明挖区间，1.66 亿）、漳州先期标（龙海站）同步挂网。 参加漳州段盾构专题会。 2025.9.21 先期标结果：泉州中建三局、厦门中铁一局、漳州中交隧道局。 2025.11.23 月底启动初步设计评审，土建招标需施工图完成后开展，预计由年底推迟至 2026 年二季度。 2026.1.16 与铁一院对接，厦门段出岛隧道拟用泥水 / TBM 双模盾构，重新提交客户需求信息。 2026.2.13 拜访中铁建福建股指，R1 线预计 2026 年 6 月招标。近期有消息称盾构直径改回 8 米 3，2月4日组织了进出岛隧道施工专家会。 2026.3.15 厦漳泉R1线全线要求在6月份动工，预计在5月份招标。 2026.3.30 整理国内8.3米、8.6米盾构机存量。 | X65: 配合铁建股指承揽项目 | Y65: 施工图设计阶段 | Z65: 核心问题：泉州段什么时候开标，采用什么模式销售、租赁盾构机。 工作思路：积极对接泉州轨道交通集团，探索盾构机转销、转租模式。 关键点：说服泉州轨道交通集团采纳盾构机转销、转租模式，签订合作协议。 行动计划：尽快促成双方高层拜访。 | AA65: 重大信息（Ⅰ级） | AB65: 周斌 | AE65: 接口专用帐号 | AF65: 跟进中 | AG65: 周斌
A66: 46111 | B66: 2025-08-11 08:54:11 | C66: XM-2025081120013 | D66: 合流污水支线1.4标 | F66: 区间长度874m，56m小转弯，前期已报价，初定竞争性谈判模式，预计年底启动 | G66: 区间长度874m，56m小转弯，ZTE4330-1 | H66: 水利水电-0 | I66: 掘进机事业部 | J66: 华东区域 | L66: 上海 | M66: 0.2000000000 | N66: 上海城投水务集团有限公司 | Q66: ZTE4300-1-(/); | R66: 2025-12-31 | S66: CNY 20,000,000.000 | T66: 赵宇瑄 | U66: 穆华清 | W66: 支线1.4标，2026年12月进场，区间长度874m，56m小转弯，前期已报价，客户拟分包给上海力行，力行打包价约22000元/m，包含人工及盾构、后配套、行车吊装等设备 | X66: 与上海城建进一步测算施工成本，推动城建自己施工 | Y66: 项目施工中标公示 | Z66: 支线1.4标，2026年12月进场，区间长度874m，56m小转弯，前期已报价，客户拟分包给上海力行，力行打包价约22000元/m，包含人工及盾构、后配套、行车吊装等设备 | AA66: 一般信息（Ⅲ级） | AB66: 赵宇瑄 | AE66: 赵宇瑄 | AF66: 跟进中 | AG66: 赵宇瑄
A67: 46111 | B67: 2025-11-14 17:28:39 | C67: XM-2025111420712 | D67: 上海轨道交通19号线 | F67: 中交隧道局4台ZTE6830 (2027-5-1);区间长度单线1200米+1300米 上海基础4台ZTE6830 (2027-6-30);区间长度单线400（370米转弯）+780（380米转弯）+660（400米转弯）+1030（350米转弯）+1145（450米转弯）米； 中铁十四局1台6.6米土压盾构，区间长度单线1644米（一级重大） | G67: / | H67: 地铁-5 | I67: 掘进机事业部 | J67: 华东区域 | L67: 上海 | M67: 3.0000000000 | N67: 上海申通地铁集团有限公司 | R67: 2027-01-31 | S67: CNY 5,000,000.000 | T67: 赵宇瑄 | W67: 中交隧道局4台ZTE6830 (2027-5-1);区间长度单线1200米+1300米 上海基础4台ZTE6830 (2027-6-30);区间长度单线400（370米转弯）+780（380米转弯）+660（400米转弯）+1030（350米转弯）+1145（450米转弯）米； 中铁十四局1台6.6米土压盾构，区间长度单线1644米（一级重大） | X67: 1、其他标段4月13日前与项目对接，了解设备筹备情况 2、上海基础4月3日前出具DZ176-178维修改造方案及报价 3、上海基础4月10日前与王凯进行商务交流 | Y67: 项目施工中标公示 | Z67: 中交隧道局4台ZTE6830 (2027-5-1);区间长度单线1200米+1300米 上海基础4台ZTE6830 (2027-6-30);区间长度单线400（370米转弯）+780（380米转弯）+660（400米转弯）+1030（350米转弯）+1145（450米转弯）米； 中铁十四局1台6.6米土压盾构，区间长度单线1644米（一级重大） | AA67: 一般信息（Ⅲ级） | AB67: 赵宇瑄 | AE67: 赵宇瑄 | AF67: 跟进中 | AG67: 赵宇瑄
A68: 46107 | B68: 2025-08-15 10:20:59 | C68: XM-2025081520064 | D68: 上海轨道交通27号线（浦南线） | F68: 起点陆家嘴，终点临港自贸区金融湾，一期位于浦东新区内，全长79公里，设车站14座。 | G68: 起点陆家嘴，终点临港自贸区金融湾，一期位于浦东新区内，全长79公里，设车站14座。 | H68: 地铁-5 | I68: 掘进机事业部 | J68: 华东区域 | L68: 上海 | M68: 200.0000000000 | N68: 上海申通地铁集团有限公司 | O68: 上海隧道院 | P68: 上海隧道院 | R68: 2027-12-31 | S68: CNY 130,000,000.000 | T68: 赵宇瑄 | W68: 已对接上海隧道院，线路处于设计阶段，预计2026年施工招标，此线路已纳入四期规划 | X68: 定期与上海隧道院沟通，跟进项目最新情况 | Y68: 施工图设计阶段 | Z68: 已对接上海隧道院，线路处于设计阶段，预计2026年施工招标，此线路已纳入四期规划 | AA68: 一般信息（Ⅲ级） | AB68: 赵宇瑄 | AE68: 赵宇瑄 | AF68: 跟进中 | AG68: 赵宇瑄
A69: 46107 | B69: 2025-08-15 10:18:46 | C69: XM-2025081520063 | D69: 燃气过江隧道 | F69: 过江管隧道长度16.3~17.2km。隧道外直径4~4.8m，隧道底板最大埋深约-68m | G69: 过江管隧道长度16.3~17.2km。隧道外直径4~4.8m，隧道底板最大埋深约-68m | H69: 其他-13 | I69: 掘进机事业部 | J69: 华东区域 | L69: 上海 | M69: 50.0000000000 | N69: 上海燃气公司 | O69: 城建院 | R69: 2027-08-31 | S69: CNY 50,000,000.000 | T69: 赵宇瑄 | W69: 与S7公路隧道平行，前期可研阶段，业主与设计院来司考察和技术交流，效果良好，后续将配合施工单位跟进项目。 | X69: 1、4月3日拜访上海城建院跟进最新进展 | Y69: 定测及初步设计阶段 | Z69: 与S7公路隧道平行，前期可研阶段，业主与设计院来司考察和技术交流，效果良好，后续将配合施工单位跟进项目。 | AA69: 一般信息（Ⅲ级） | AB69: 赵宇瑄 | AE69: 赵宇瑄 | AF69: 跟进中 | AG69: 赵宇瑄
A70: 46107 | B70: 2025-08-16 10:28:05 | C70: XM-2025081620059 | D70: 上海原水西环线南北段项目焊接机器人设备 | F70: 原水西环线大概50km，35km是盾构内敷设钢管，DN3400mm管径 | G70: / | H70: 水利水电-0 | I70: 电气与智能研究设计院 | J70: 华东区域 | L70: 上海 | M70: 0.0050000000 | N70: 上海城投水务集团有限公司 | R70: 2026-01-31 | S70: CNY 1,000,000.000 | T70: 赵宇瑄 | W70: 拟用焊接机器人设备，已与上海城投水务、上海基础、上海机施进行技术交流 | X70: 1、4月10日前约见上海城投水务，交流如何推动焊接机器人应用 | Y70: 商务交流 | Z70: 拟用焊接机器人设备，已与上海城投水务、上海基础、上海机施进行技术交流 | AA70: 一般信息（Ⅲ级） | AB70: 赵宇瑄 | AE70: 赵宇瑄 | AF70: 跟进中 | AG70: 赵宇瑄
A71: 46107 | B71: 2026-01-25 16:53:31 | C71: XM-2026012521261 | D71: 上海市临海电力项目 | F71: 位置在上海市闵浦大桥东西两侧，区间四段，5.2米盾构1.7km+7.8米盾构2km+2段6.6米盾构1.5km | G71: 区间四段，5.2米盾构1.7km+7.8米盾构2km+2段6.6米盾构1.5km | H71: 电力-14 | I71: 掘进机事业部 | J71: 华东区域 | L71: 上海 | M71: 10.0000000000 | N71: 国家电网 | R71: 2027-06-30 | S71: CNY 120,000,000.000 | T71: 赵宇瑄 | W71: 拜访上海市政院，由市政一院负责前期，已前往北京国网多次论证，预计设计招标2026年底 | X71: 1、4月10日前拜访上海市政院了解最新进展； | Y71: 项目立项阶段（预可研，初测及可研，环评） | Z71: 拜访上海市政院，由市政一院负责前期，已前往北京国网多次论证，预计设计招标2026年底 | AA71: 一般信息（Ⅲ级） | AB71: 赵宇瑄 | AE71: 赵宇瑄 | AF71: 跟进中 | AG71: 赵宇瑄
A72: 46107 | B72: 2021-07-23 19:08:29 | C72: XM-202107237599 | D72: 上海南北通道 | F72: 大盾构区间约13.5千米，单管双层布置，圆隧道外径15米，内径13.7米。最小转弯半径500米。 | G72: 浦西段2.25千米，越江段2.26千米，共线段5.5千米，浦东段3.5千米 | H72: 公路 | I72: 掘进机研发运营中心 | J72: 华东区域 | L72: 上海 | M72: 6.0000000000 | N72: 上海城投公路投资集团有限公司 | O72: 上海市政院 | R72: 2026-10-31 | S72: CNY 100,000,000.000 | T72: 穆华清 | U72: 赵宇瑄 | W72: 由于南北通道规划区间有360m小转弯，原有盾构可能涉及改造。上海隧道自有3台泥水/土压，上海基础自有1台泥水。目前南北通道浦西段基坑已中标公示，上海建工中标 | X72: 1、4月30日前拜访业主了解最新进展； | Y72: 定测及初步设计阶段 | Z72: 由于南北通道规划区间有360m小转弯，原有盾构可能涉及改造。上海隧道自有3台泥水/土压，上海基础自有1台泥水。目前南北通道浦西段基坑已中标公示，上海建工中标 | AA72: 重点信息（Ⅱ级） | AB72: 穆华清 | AE72: 丁艳林 | AF72: 跟进中 | AG72: 赵宇瑄
A73: 46107 | B73: 2021-10-21 09:52:43 | C73: XM-202110218365 | D73: 上海市南枫线 | F73: 自南汇支线金融服务区站，经上海自贸区临港新片区，奉贤奉城镇，奉贤新城，金山区亭林镇，朱泾镇，枫泾镇，至枫泾站。全长93公里，隧道27公里 | G73: 27公里隧道 | H73: 轨道交通 | I73: 掘进机研发运营中心 | J73: 华东区域 | L73: 上海 | M73: 280.0000000000 | N73: 上海申铁 | O73: 中铁上海设计院 | R73: 2026-10-31 | S73: CNY 15,000,000.000 | T73: 穆华清 | U73: 赵宇瑄 | W73: 中铁上海院总体设计，目前初设已初步完成，预计招标时间为2026年下半年 | X73: 1、4月25日前拜访业主、设计院跟进施工招标动态变化； 2、4月底前梳理同规格设备市场动向。 | Y73: 施工图设计阶段 | Z73: 中铁上海院总体设计，目前初设已初步完成，预计招标时间为2026年下半年 | AA73: 一般信息（Ⅲ级） | AB73: 赵宇瑄 | AE73: 赵宇瑄 | AF73: 跟进中 | AG73: 赵宇瑄
A74: 46107 | B74: 2026-01-25 16:48:37 | C74: XM-2026012521270 | D74: 上海城建库管1.6标 | F74: 青草沙-陈行库管连通工程KG1.6标一井一区间，3444m，隧道外径φ6200mm，内径φ5500mm，为单线隧道。平面最小转弯半径R=500m | G74: 青草沙-陈行库管连通工程KG1.6标一井一区间，3444m，隧道外径φ6200mm，内径φ5500mm，为单线隧道。平面最小转弯半径R=500m | H74: 水利水电-0 | I74: 掘进机事业部 | J74: 华东区域 | L74: 上海 | M74: 0.3000000000 | N74: 上海城投水务 | R74: 2026-07-31 | S74: CNY 20,000,000.000 | T74: 赵宇瑄 | W74: 1、上海城建市政意向租赁单价4000元/延米，我司给出报价4500元/米，事业部建议在4350元/m能成交 2、竞争对手上海力行、辽宁三三、天津一重，客户倾向于上海力行 | X74: 1、在设备确定前持续跟进城建市政与各单位洽谈情况，如有机会及时采取策略 | Y74: 设备招标阶段 | Z74: 1、上海城建市政意向租赁单价4000元/延米，我司给出报价4500元/米，事业部建议在4350元/m能成交 2、竞争对手上海力行、辽宁三三、天津一重，客户倾向于上海力行 | AA74: 一般信息（Ⅲ级） | AB74: 赵宇瑄 | AE74: 赵宇瑄 | AF74: 跟进中 | AG74: 赵宇瑄
A75: 46107 | B75: 2025-08-15 10:16:38 | C75: XM-2025081520062 | D75: 蒙电入沪 | F75: 库布齐—上海±800千伏特高压GIL管廊工程隧道总长11.3km，江中段约10km，管片外径初定12.5m | G75: 库布齐—上海±800千伏特高压GIL管廊工程隧道总长11.3km，江中段约10km，管片外径初定12.5m | H75: 电力-14 | I75: 掘进机事业部 | J75: 华东区域 | L75: 上海 | M75: 50.0000000000 | N75: 国家电网上海分公司 | O75: 城建院 | R75: 2026-11-30 | S75: CNY 80,000,000.000 | T75: 赵宇瑄 | W75: 中铁隧道局与上海隧道院配合密切，中铁隧道局在北沿江高铁项目已建成的管片厂等配套设备可直接投入该项目使用，14局也在跟进，拜访隧道院管院长，土建预计2026年上半年招标，2026年底进场 | X75: 1、4月10日前与上海隧道院跟进项目招标情况； 2、4月30日前与业主建立联系 3、4月30日前与十四局大盾构公司对接联系，共同推进项目落地 | Y75: 定测及初步设计阶段 | Z75: 中铁隧道局与上海隧道院配合密切，中铁隧道局在北沿江高铁项目已建成的管片厂等配套设备可直接投入该项目使用，14局也在跟进 | AA75: 一般信息（Ⅲ级） | AB75: 赵宇瑄 | AE75: 赵宇瑄 | AF75: 跟进中 | AG75: 赵宇瑄
A76: 46107 | B76: 2025-04-28 15:57:52 | C76: XM-2025042819326 | D76: 上海嘉闵线北延 | F76: 初步设计阶段，预计招标时间2026年底 | G76: 预计区间长度12km | H76: 城建-1 | I76: 掘进机事业部 | J76: 华东区域 | L76: 上海 | M76: 20.0000000000 | N76: 上海申铁建设集团有限公司 | R76: 2027-03-31 | S76: CNY 15,000,000.000 | T76: 赵宇瑄 | W76: 施工单位待定，预估租赁2台9米土压盾构 | X76: 跟进施工标段招标时间 | Y76: 项目施工招标阶段 | Z76: 施工单位待定，预估租赁2台9米土压盾构 | AA76: 一般信息（Ⅲ级） | AB76: 赵宇瑄 | AE76: 赵宇瑄 | AF76: 跟进中 | AG76: 赵宇瑄
A77: 46107 | B77: 2021-10-21 09:41:03 | C77: XM-202110218363 | D77: 上海地铁20号线 | F77: 共设车站16座，全长28km，串联浦东新区三大功能区的南北向径向市区线 | G77: 6.6米土压盾构机凌兆新村站→东方体育中心1640m 11.3米泥水盾构区间224m | H77: 轨道交通 | I77: 掘进机研发运营中心 | J77: 华东区域 | L77: 上海 | M77: 393.0000000000 | N77: 上海申通地铁 | O77: 上海隧道工程轨道交通设计院 | R77: 2027-01-31 | S77: CNY 10,000,000.000 | T77: 穆华清 | U77: 赵宇瑄 | W77: 上海基础4台ZTE6830 (2027-8-30);区间长度单线1700（450米转弯）+880米（375米转弯）+1070（380米转弯）+700（450米转弯）2台ZTE6830 (2027-12-30);区间长度单线1400（450米转弯）+1900米（600米转弯） 中铁十一局2台ZTE6830 (2027-4-30);初步了解使用23号线自有设备DZ360/361，18年初出厂 中铁十四局，已对接项目经理，需求4台6.6米土压盾构，区间长度单线830（300米转弯）+780+1300米（350米转弯） | X77: 1、所有标段4月20日前与项目对接，了解设备筹备情况 2、上海基础标段4月3日前出具DZ176-178维修改造方案及报价 3、上海基础4月10日前与王凯进行商务交流 | Y77: 项目施工中标公示 | Z77: 上海基础4台ZTE6830 (2027-8-30);区间长度单线1700（450米转弯）+880米（375米转弯）+1070（380米转弯）+700（450米转弯）2台ZTE6830 (2027-12-30);区间长度单线1400（450米转弯）+1900米（600米转弯） 中铁十一局2台ZTE6830 (2027-4-30);初步了解使用23号线自有设备DZ360/361，18年初出厂 中铁十四局，已对接项目经理，需求4台6.6米土压盾构，区间长度单线830（300米转弯）+780+1300米（350米转弯） | AA77: 一般信息（Ⅲ级） | AB77: 赵宇瑄 | AE77: 赵宇瑄 | AF77: 跟进中 | AG77: 赵宇瑄
A78: 46107 | B78: 2026-01-25 16:43:21 | C78: XM-2026012521260 | D78: 上海原水西环线1.2标 | F78: 463m+100m,1台5.2米主动铰接土压盾构机 | G78: 463m+100m,1台5.2米主动铰接土压盾构机 | H78: 水利水电-0 | I78: 掘进机事业部 | J78: 华东区域 | L78: 上海 | M78: 0.4000000000 | N78: 上海城投水务 | R78: 2026-03-31 | S78: CNY 20,000,000.000 | T78: 赵宇瑄 | W78: 已对接项目经理以及分包负责人，客户需求主动铰接5.2米土压盾构机，目前市场询价中，低价优先；已核实我司没有符合要求的设备 | X78: 1、4月3日前拜访项目经理，跟进客户询价情况，争取做维修改造 | Y78: 商务交流 | Z78: 1、4月3日前拜访项目经理，跟进客户询价情况，争取做维修改造 | AA78: 一般信息（Ⅲ级） | AB78: 赵宇瑄 | AE78: 赵宇瑄 | AF78: 跟进中 | AG78: 赵宇瑄
A79: 46107 | B79: 2025-08-11 08:29:46 | C79: XM-2025081120030 | D79: 上海路桥库管项目1.5标 | F79: 原水西环线北段起点，5#井-4#井区间长度2377m，管片内外径6200/5500，2026年底或27年初设备进场 | G79: 1.6km，6.2米管片外径小转弯土压盾构机 | H79: 城建-1 | I79: 掘进机事业部 | J79: 华东区域 | L79: 上海 | M79: 0.3000000000 | N79: 上海城投水务集团有限公司 | Q79: ZTE6200-1-(2026-06-30); | R79: 2025-12-31 | S79: CNY 20,000,000.000 | T79: 赵宇瑄 | W79: 1、2027年4月进场 2、3月23日已报价，3485万井底交货 | X79: 1、4月3日前拜访上海路桥公用建设公司副总张涛，跟进各家报价情况（中交、装备、海瑞克） 2、根据了解的报价情况拜访上海路桥集团领导 | Y79: 设计联络 | Z79: 1、4月3日前拜访上海路桥公用建设公司副总张涛，跟进各家报价情况（中交、装备、海瑞克） 2、根据了解的报价情况拜访上海路桥集团领导 | AA79: 一般信息（Ⅲ级） | AB79: 赵宇瑄 | AE79: 赵宇瑄 | AF79: 跟进中 | AG79: 赵宇瑄
A80: 46101 | B80: 2025-11-05 14:43:33 | C80: XM-2025110520640 | D80: 中铁十五局集团有限公司 2025-2026年度钢模板、挂篮模板、套筒、波纹管、锚杆等物资框架协议采购 | F80: 中铁十五局集团有限公司是一支位居世界500强第43位的中国铁建旗下的基建劲旅，是集设计、施工、科研为一体的国有建筑工程总承包企业，上海市首家拥有铁路工程施工总承包特级、公路工程施工总承包特级（两个）、市政公用工程施工总承包特级、建筑工程施工总承包特级的五特级企业。集团公司下设16个全资子公司，另设轨道交通运营公司、城建设计研究院2个分公司、8个区域总部，1个海外及央企（JM）事业总部。 在管理体制上，集团公司全面推行精细化管理模式，在做精做优工程主业的基础上，不断延伸产业链条，精心打造“深地空间、地下交通枢纽、智慧停车、新能源、城市更新、超高性能混凝土、铁建石油、运营维护、PC产业园、园林建筑”等“十大品牌”，培育成型八大业务板块，即工程承包板块、铁路运营板块、资本运营板块、房地产开发板块、物流贸易板块、工业制造板块、海外工程板块、勘察设计板块等，年施工能力达1000亿元以上。 | G80: 无 | H80: 绿色建材-10 | I80: 矿山装备事业部 | J80: 华东区域 | L80: 江西 | M80: 4.6700000000 | N80: 中铁十五局集团有限公司 | Q80: 带式输送机输送系统-1-(/); | R80: 2025-11-17 | S80: CNY 1.000 | T80: 陈浩 | V80: 设备已中标 | W80: 已经与十五局集团签订了战略采购框架协议。 | X80: 完成战略采购框架协议的合同归档。 | Y80: 设备已中标 | Z80: 已经与十五局集团签订了战略采购框架协议。 | AA80: 一般信息（Ⅲ级） | AB80: 陈浩 | AE80: 陈浩 | AF80: 跟进中 | AG80: 陈浩
A81: 46083 | B81: 2026-01-26 12:11:36 | C81: XM-2026012621262 | D81: 福建马坑矿业液压掘进台车采购需求 | F81: 福建马坑铁矿需求3台液压掘进台车，已于2026年1月21日挂网，原计划2月5日开标，现延迟到2月27日开标。 | G81: / | H81: 非煤矿山-11 | I81: 特种装备事业部 | J81: 华东区域 | L81: 福建 | M81: 20.0000000000 | N81: 福建马坑矿业股份有限公司 | Q81: CYTJ45C-3-(2026-03-31); | R81: 2026-03-31 | S81: CNY 3,600,000.000 | T81: 杨志胜 | V81: 设备招标阶段 | W81: 福建马坑铁矿需求3台液压掘进台车，已于2026年1月21日挂网，2月27日开标。我司因发动机功率无法满足技术要求，同时福建亿钻代理华泰，经与事业部综合研判决定放弃投标。3月1日中标公示，浙江华泰375万中标。 | X81: 继续开展与马坑铁矿的高层对接，处理中深孔设备后续事宜。 | Y81: 设备未中标 | Z81: 已对接马坑铁矿生产部和采购部。 | AA81: 重点信息（Ⅱ级） | AB81: 杨志胜 | AE81: 杨志胜 | AF81: 跟进中 | AG81: 杨志胜
A82: 46053 | B82: 2024-03-02 21:01:27 | C82: XM-2024030216331 | D82: 上虞区曹娥江市政过江隧道项目 | F82: 本项目起于虞兴路-五星东路路口，止于市民大道-称山南路路口，全长约1830m，盾构段长约795m；采用11.3米管片外径泥水盾构； | G82: 全长约1830m，盾构段长约795m | H82: 城建-1 | I82: 掘进机事业部 | J82: 华东区域 | L82: 浙江 | M82: 20.1900000000 | N82: 绍兴市上虞区交通集团有限公司 | O82: 中国电建集团华东勘测设计研究院有限公司 | Q82: 11.3米管片外径泥水平衡盾构机-1-(/); | R82: 2026-12-31 | S82: CNY 10,000,000.000 | T82: 刘新峥 | W82: 目前该项目正在申请专项债市发改委已通过，但省发改委未批复； | X82: 跟进项目资金到位情况，了解项目重新启动的时间 | Y82: 施工图设计阶段 | Z82: 1、核心问题：项目原计划同绍兴地铁2号线一同招标，但由于上虞区资金紧张，目前省发改委还未批复。 2、工作思路：重点配合系统内单位投标，了解各家自有设备情况。 3、关键点：施工标中标单位；中标单位是否有自有设备 4、行动计划：拜访业主单位，让其对我司产品有初步了解，跟进其实际施工招标进展时间；对接设计院盾构区间负责人郑浩龙，提供设备的设计参数，配合其做招标文件，多与系统内单位进行沟通对接交换信息跟进进展。 | AA82: 一般信息（Ⅲ级） | AB82: 刘新峥 | AE82: 刘新峥 | AF82: 跟进中 | AG82: 刘新峥
A83: 46053 | B83: 2024-04-27 14:29:03 | C83: XM-2024042716658 | D83: 台州市域铁路S4线 | F83: 台州市域铁路S4线起于腾云路，往南经台州机场，终至温岭新河镇，线路全长约26km，其中地下段6.6km，高架线25.4km；全线设站8座，其中地下站4座，高架站4座；线路在新河南站与规划市域铁路S5线贯通，本线于新河镇东侧新建车辆段一座。 | G83: 地下段6.6km | H83: 轨道交通-12 | I83: 掘进机事业部 | J83: 华东区域 | L83: 浙江 | M83: 136.0000000000 | N83: 台州市轨道交通 | Q83: ZTE8800-2-(2026-10-07); | R83: 2027-10-14 | S83: CNY 20,000,000.000 | T83: 沈腾飞 | W83: 拜访台州交通，了解项目进展及隧道情况，目前预可研编制中，预计地下段左右线共计6km，近五年不会开工。 | X83: 跟进项目工可获批进展。 | Y83: 项目立项阶段（预可研，初测及可研，环评） | Z83: 核心问题：1、地下段较短，约6km；2、资金较紧张、3、铁四院在工可阶段。 工作思路：跟踪项目获批情况 关键点：1、因台州市资金紧张，关注S2线施工资金是否按期支付；2、项目获批时间 行动计划：跟踪工可最新进展。 | AA83: 一般信息（Ⅲ级） | AB83: 沈腾飞 | AE83: 沈腾飞 | AF83: 跟进中 | AG83: 沈腾飞
A84: 46053 | B84: 2025-03-28 08:41:46 | C84: XM-2025032819050 | D84: 天河抽水蓄能电站 | F84: 总投资80亿元，中电建投资，2022年已完成项目公司成立，目前项目暂未获批，宁波市列为今年启动项目。排水廊道长度约3km。电建华东院负责前期。 | G84: 3km左右3.5米排水廊道 | H84: 水利水电-0 | I84: 掘进机事业部 | J84: 华东区域 | L84: 浙江 | M84: 80.0000000000 | N84: 浙江宁海中电建天河抽水蓄能有限公司 | O84: 中电建华东院 | P84: 待定 | Q84: ZTT3530-1-(2027-07-22); | R84: 2027-06-02 | S84: CNY 33,000,000.000 | T84: 沈腾飞 | W84: 中电建投资，2022年已完成项目公司成立，目前项目规划中，暂未获批，预计十五五获批。项目无最新进展。 | X84: 跟踪项目获批进展。 | Y84: 项目立项阶段（预可研，初测及可研，环评） | Z84: 持续对接电建华东院设计负责人王东峰，目前暂未明确项目获批时间。 | AA84: 一般信息（Ⅲ级） | AB84: 沈腾飞 | AE84: 沈腾飞 | AF84: 跟进中 | AG84: 沈腾飞
A85: 46022 | B85: 2023-06-03 13:28:53 | C85: XM-2023060313941 | D85: 温武吉铁路 | F85: 线路全长689公里，总投资800亿元，设计时速160km/h，预留200km/h条件。 | G85: 暂未收集 | H85: 铁路-2 | I85: 特种装备事业部 | J85: 华东区域 | L85: 福建 | M85: 800.0000000000 | N85: 东南沿海铁路福建公司 | O85: 前期预可研中国铁路设计集团公司 | Q85: HZS180-20-(/); | R85: 2026-12-31 | S85: CNY 10,000,000.000 | T85: 杨志胜 | W85: 地方三省主张时速160公里双线方案，国铁集团因客货运量预测偏低倾向120时速单线方案。2024年底国家发改委支持“单线预留双线”方案，即初期按单线建设，但桥梁、隧道等基础设施按双线标准设计，未来可升级。目前仍处方案论证阶段。 | X85: 对接设计院和业主单位，了解项目前期筹备情况。 | Y85: 项目立项阶段（预可研，初测及可研，环评） | Z85: 地方三省主张时速160公里双线方案，国铁集团因客货运量预测偏低倾向120时速单线方案。2024年底国家发改委支持“单线预留双线”方案，即初期按单线建设，但桥梁、隧道等基础设施按双线标准设计，未来可升级。目前仍处方案论证阶段。 | AA85: 重点信息（Ⅱ级） | AB85: 陆顺 | AE85: 陆顺 | AF85: 跟进中 | AG85: 杨志胜
A86: 46022 | B86: 2023-06-04 14:39:11 | C86: XM-2023060413970 | D86: 新干至兴国高速公路 | F86: 长约186公里，起于阳樟高速终点，与东昌高速十字交叉，终于泉南高速，与兴国至桂东高速顺接。 | G86: 全线隧道总长度为11.475公里（11475米），包含5座隧道。 | H86: 公路-4 | I86: 特种装备事业部 | J86: 华东区域 | L86: 江西 | M86: 0.0000000000 | N86: 江西省交通投资集团有限责任公司项目建设管理公司 | O86: 江西省交通设计研究院有限责任公司 | P86: 中铁和中交系统各工程局 | Q86: 搅拌站-1-(/); | R86: 2026-06-30 | S86: CNY 0.000 | T86: 杨志胜 | W86: 特许经营中标结果已公示，中铁系统和中交系统联合体中标，具体标段划分暂未明确，项目暂未开工建设。 | X86: 目前标段暂未划分，未组织进场，下一步计划对接施工单位，摸排设备需求情况。没有系统内单位中标，不做重点跟进。 | Y86: 商务交流 | Z86: 特许经营中标结果已公示，中铁系统和中交系统联合体中标，具体标段划分暂未明确。 | AA86: 一般信息（Ⅲ级） | AB86: 杨志胜 | AE86: 郭亚楠 | AF86: 跟进中 | AG86: 杨志胜
A87: 46022 | B87: 2023-06-04 14:52:37 | C87: XM-2023060413957 | D87: 寻乌至全南高速公路西延段 | F87: 项目路线全长 53.488km，设计速度 100km/h，采用双向四车道高速公路设计标准建设，路基宽度 26m。设置互通式立交 4 处，其中枢纽互通 1处，一般式落地互通 3 处；连接线 2km/3 处；设置服务区 1 处，设置桥梁13568m/23 座，隧道 7835m/5 座。项目投资估算总金额约 73.8455 亿元（项目建设规模及投资估算金额最终以政府核准为准）。 | G87: 隧道 7835m/5 座 | H87: 公路-4 | I87: 特种装备事业部 | J87: 华东区域 | L87: 江西 | M87: 96.0000000000 | N87: 赣州交通控股集团有限公司 | O87: 江西省赣南公路勘察设计院有限公司 中交公路规划设计院有限公司 安徽省交通规划设计研究总院股份有限公司 | P87: 湖北路桥（牵头人）、陕西路桥、宁夏交建、湖北交投联合体 | Q87: 搅拌站-1-(/); | R87: 2026-06-30 | S87: CNY 0.000 | T87: 杨志胜 | W87: 项目模式为特许经营，经营期限30年。2025年9月20日中标结果公示，湖北路桥（牵头人）、陕西路桥、宁夏交建、湖北交投联合体中标，暂未组织进场。 | X87: 待项目组织进场后，对接项目部，跟进拱架、湿喷等设备需求。 | Y87: 商务交流 | Z87: 前期对接了系统内各单位，因铁建无法投资，系统内单位没有参与。 | AA87: 一般信息（Ⅲ级） | AB87: 杨志胜 | AE87: 郭亚楠 | AF87: 跟进中 | AG87: 杨志胜
A88: 46022 | B88: 2023-06-04 15:31:24 | C88: XM-2023060413983 | D88: 横峰抽水蓄能电站 | F88: 横峰抽水蓄能电站计划总投资约100亿元，该电站于10月12日签约，项目位于横峰县葛源镇关田村。初步预计装机容量1200MW，装机4台，单机容量300MW，工程等别为一级。 | G88: 设斜井、引水洞、尾水洞等。 | H88: 水利水电-0 | I88: 特种装备事业部 | J88: 华东区域 | L88: 江西 | M88: 100.0000000000 | N88: 葛洲坝集团 | R88: 2026-12-31 | S88: CNY 0.000 | T88: 陈浩 | W88: 2022年10月，葛洲坝集团与横峰县政府签署投资建设意向协议，总投资约100亿元。因前期上库坐标错误导致环境制约因素未达标，需重新调整方案。目前正在推进前期工作。 | X88: 对接葛洲坝集团江西经营部，跟进项目启动进展。 | Y88: 施工图设计阶段 | Z88: 已经与设计单位建立联系。 | AA88: 一般信息（Ⅲ级） | AB88: 杨志胜 | AE88: 郭亚楠 | AF88: 跟进中 | AG88: 杨志胜
A89: 46022 | B89: 2024-03-03 11:12:22 | C89: XM-2024030316329 | D89: 江西抚州宜黄县二都镇高山饰面用花岗岩矿矿山建设+生产加工项目 | F89: 矿区采用露天开采方式，年产矿废石量约 40.82万立方米，全部用于加工区生产成品骨料；矿区面积 0.2407km2，一期开采深 度+860米至+700 米，资源量1345万立方米 | G89: 无 | H89: 非煤矿山-11 | I89: 矿山装备事业部 | J89: 华东区域 | L89: 江西 | M89: 11.0000000000 | N89: 江西省茂新矿业有限责任公司 | O89: / | P89: 中铁二十三局三公司 | Q89: 砂石骨料生产线-1-(/); | R89: 2026-12-31 | S89: CNY 0.000 | T89: 杨志胜 | W89: 中铁二十三局和中铁五院再次中标，中标金额11亿，经了解是为了年中完成任务，项目没有启动计划。 | X89: 保持与二十三局江西经营部的对接，关注项目启动情况。 | Y89: 商务交流 | Z89: 已对接二十三局江西经营部，短期内没有启动计划。 | AA89: 一般信息（Ⅲ级） | AB89: 杨志胜 | AE89: 郭亚楠 | AF89: 跟进中 | AG89: 杨志胜
A90: 46022 | B90: 2024-04-29 13:18:19 | C90: XM-2024042916710 | D90: G220武穴至瑞昌过江通道 | F90: 路线全长12.915公里，估算总投资为70.51亿元，其中武穴市负责长江大桥段和武穴境接线工程的建设，九江境内6.7公里，一级公路标准设计。 | G90: 无 | H90: 公路-4 | I90: 特种装备事业部 | J90: 华东区域 | L90: 江西 | M90: 70.5100000000 | N90: 瑞昌市交通运输局 | O90: 中交第二公路勘察设计研究院有限公司 | P90: 待定 | Q90: 搅拌站-1-(/); | R90: 2026-06-30 | S90: CNY 1,300,000.000 | T90: 杨志胜 | W90: 湖北段已开工，江西段已完成征拆，正在做招标前准备工作，预计2026年2季度施工招标。 | X90: 重点对接江西股指和系统内个单位，跟进招标进展。 | Y90: 施工图设计阶段 | Z90: 前期对接了江西股指及18局、11局等单位。 | AA90: 一般信息（Ⅲ级） | AB90: 杨志胜 | AE90: 郭亚楠 | AF90: 跟进中 | AG90: 杨志胜
A91: 46022 | B91: 2024-04-29 13:28:18 | C91: XM-2024042916711 | D91: 湖口至九江跨湖二通道 | F91: 起于既有S22都九高速与S20彭湖高速的湖口枢纽，自东向西跨越鄱阳湖，沿庐山北麓、九江中心城区南缘间布线，终点接既有G70福银高速与G56杭瑞高速的九江枢纽，规划线路全长约46公里，其中跨湖段约19公里（兼顾G351跨湖）、城区段约27公里。 | G91: / | H91: 公路-4 | I91: 特种装备事业部 | J91: 华东区域 | L91: 江西 | M91: 24.0000000000 | N91: 江西省交通投资集团有限责任公司 | O91: 中交第一公路勘察设计研究院 | P91: 待定 | Q91: 搅拌站-1-(/); | R91: 2026-09-30 | S91: CNY 0.000 | T91: 杨志胜 | W91: 湖口至九江跨湖二通道项目还处于深化工可研究阶段，需继续完善路线方案，做好投融资模式比选论证。 | X91: 继续对接江西股指和中交一院，掌握项目最新进展。 | Y91: 项目立项阶段（预可研，初测及可研，环评） | Z91: 湖口至九江跨湖二通道项目还处于深化工可研究阶段，需继续完善路线方案，做好投融资模式比选论证。 | AA91: 一般信息（Ⅲ级） | AB91: 杨志胜 | AE91: 郭亚楠 | AF91: 跟进中 | AG91: 杨志胜
A92: 46022 | B92: 2024-04-29 14:17:49 | C92: XM-2024042916713 | D92: 萍乡市自然资源矿业开发有限公司上栗县楚山绿色建材项目 | F92: 拟建设总年产量为980万吨骨料，其中600万吨作为建筑用砂石骨料，380万吨作为水泥用石灰石。建设内容分为四部分：（1）采矿基建期配套，含表土剥离、矿山开拓系统、矿山运输系统、建设期排水系统、排土场等矿山基建工程；（2）骨料线，粗碎车间、中/细碎车间、除土/检查筛分车间、石灰石碎石库、成品筛分车间、选粉制砂及石粉散装、土堆棚、骨料成品储存库车间、辅助生产设施等；（3）场外重载交通运输公路，从建设场地连接到s308省道，下穿昌栗高速，路线全长约2.8km，按二级公路技术标准设计，设计速度40km/h，一般路基宽8.5m，昌栗高速以北设有爬坡车道路基宽17m，设有明洞1处；（4）远期预留廊道工程，年运输能力200万吨，计划2029年开工建设。 | G92: / | H92: 非煤矿山-11 | I92: 矿山装备事业部 | J92: 华东区域 | L92: 江西 | M92: 15.5000000000 | N92: 萍乡市自然资源矿业开发有限公司（萍乡市投发） | O92: 南昌瑀城交通设计有限公司和广西工业设计集团有限公司联合体 | P92: 待定 | Q92: 砂石骨料生产线-1-(/); | R92: 2026-09-30 | S92: CNY 0.000 | T92: 杨志胜 | W92: 已对接萍乡市矿业开发公司黄总，了解项目进展，目前还在办理相关手续，项目模式未确定，项目还处于前期准备阶段，8月份进入了用地审批程序。推进缓慢。 | X92: 项目无实质性进展，继续保持跟进。 | Y92: 定测及初步设计阶段 | Z92: 已对接对接萍乡市矿业开发公司，并引荐系统内19局和14局跟进。 | AA92: 一般信息（Ⅲ级） | AB92: 杨志胜 | AE92: 郭亚楠 | AF92: 跟进中 | AG92: 杨志胜
A93: 46022 | B93: 2025-07-31 22:48:36 | C93: XM-2025073119973 | D93: 安能二局边坡支护设备需求 | F93: 安能二局科技发展部计划申报边坡支护设备科研课题，已为客户提供我司技术方案。 | G93: 略 | H93: 水利水电-0 | I93: 特种装备事业部 | J93: 华东区域 | L93: 江西 | M93: 0.0000000000 | N93: 中国安能集团第二工程局有限公司 | Q93: MG14-ND-1-(/);KCD2-ND-1-(/); | R93: 2026-09-30 | S93: CNY 6,700,000.000 | T93: 杨志胜 | W93: 和安能二局科技部初步沟通，合作模式有待洽谈，已提供技术资料和施工视频。安能二局科技部正在推动内部科研课题立项工作，暂无最新进展。 | X93: 无最新进展，保持与二局科技部的交流对接。 | Y93: 商务交流 | Z93: 已对接安能二局科技发展部，提供了产品技术方案及施工视频。 | AA93: 一般信息（Ⅲ级） | AB93: 杨志胜 | AE93: 杨志胜 | AF93: 跟进中 | AG93: 杨志胜
A94: 46022 | B94: 2023-06-04 14:30:41 | C94: XM-2023060413968 | D94: 南昌北二环高速公路 | F94: 江西南昌北二绕城高速公路项目路线起于江西省南昌市安义县万埠镇，接在建的南昌西二绕城高速公路，经安义县万埠镇、长均乡、永修县马口镇、赣江新区中医药科创城、经开区樵舍镇、新建区金桥乡、象山镇、联圩乡、南昌县南新乡，终于福银高速南昌东绕城段的南新互通，全长约52.010公里。项目概算总投资约96.68亿元，其中建安费约65.44亿元。 | G94: 无 | H94: 公路-4 | I94: 特种装备事业部 | J94: 华东区域 | L94: 江西 | M94: 96.6800000000 | N94: 江西省交通投资集团有限责任公司项目建设管理公司 | O94: T1标段 ：中交第二公路勘察设计研究院有限公司、 T2标段 江西省交通设计研究院有限责任公司 | P94: T1标段 中交路桥建设有限公司 ;T2标段 ：江西省交通工程集团有限公司、 南昌城建集团有限公司 | Q94: 搅拌站-1-(2024-12-31); | R94: 2025-06-18 | S94: CNY 0.000 | T94: 陈浩 | W94: 该项目采取设计施工总承包的模式，12月30日挂网公示中标单位。 T1标段 中交路桥建设有限公司、 中交第二公路勘察设计研究院有限公司联合体 T2标段 江西省交通工程集团有限公司、 南昌城建集团有限公司、 江西省交通设计研究院有限责任公司联合体 | X94: 联系中标单位了解项目进场情况。 | Y94: 设计联络 | Z94: 核心问题：项目有无隧道施工设备要求。 工作思路：拜访中标单位，了解项目有无搅拌站需求。 关键点：项目有无隧道设备需求. 行动计划：拜访系中标单位及设计院，了解设备需求情况。 | AA94: 一般信息（Ⅲ级） | AB94: 杨志胜 | AE94: 郭亚楠 | AF94: 跟进中 | AG94: 陈浩
A95: 46022 | B95: 2023-06-04 14:50:23 | C95: XM-2023060413956 | D95: 上饶至德兴至婺源高速公路 | F95: 路线全长124公里，由上饶至景德镇（上饶段）高速91公里和德兴至婺源高速33公里组成。 | G95: 无 | H95: 公路-4 | I95: 交通工程装备事业部 | J95: 华东区域 | L95: 江西 | M95: 0.0000000000 | N95: 江西省交通投资集团有限责任公司项目建设管理公司 | O95: 江西省交通设计研究院有限责任公司 | P95: 待定 | Q95: 搅拌站-1-(2024-12-31); | R95: 2025-12-25 | S95: CNY 0.000 | T95: 陈浩 | W95: 通过江西股指了解到由于南丰至弋阳高速公路项目的影响,项目暂停. | X95: 持续关注项目后续进展 | Y95: 施工图设计阶段 | Z95: 核心问题：项目模式确定、项目建设资金来源、开工时间确定。 工作思路：依靠系统内单位运作。 关键点：无。 行动计划：拜访系统内单位，了解情况。 | AA95: 一般信息（Ⅲ级） | AB95: 杨志胜 | AE95: 郭亚楠 | AF95: 跟进中 | AG95: 陈浩
A96: 46022 | B96: 2023-06-04 14:57:11 | C96: XM-2023060413959 | D96: 上饶浙赣界至金溪高速公路一期工程 （浙赣界至宁上高速段） | F96: 高速公路双向六车道，全长约83公里。总投资88亿。 | G96: 无 | H96: 公路-4 | I96: 特种装备事业部 | J96: 华东区域 | L96: 江西 | M96: 88.0000000000 | N96: 江西省交通投资集团有限责任公司 | O96: 江西省交通设计研究院有限责任公司 | P96: 待定 | R96: 2025-08-20 | S96: CNY 0.000 | T96: 陈浩 | W96: 该项目目前暂未开工。 | X96: 持续关注项目后续进展 | Y96: 商务交流 | Z96: 核心问题：项目模式确定、项目建设资金来源、开工时间确定。 工作思路：依靠系统内单位运作。 关键点：无。 行动计划：拜访系统内单位，了解情况。 | AA96: 一般信息（Ⅲ级） | AB96: 杨志胜 | AE96: 郭亚楠 | AF96: 跟进中 | AG96: 陈浩
A97: 46022 | B97: 2023-06-04 14:59:23 | C97: XM-2023060413971 | D97: 瑶湖隧道 | F97: 起学苑一路，延艾溪湖二路，穿越瑶湖，往东与德昌高速立交相接。原规划的瑶湖隧道长度为5.5公里，重新规划后隧道长度缩短为3公里。 | G97: 原隧道长度为5.5公里，重新规划后隧道长度缩短为3公里。 | H97: 市政管廊-6 | I97: 特种装备事业部 | J97: 华东区域 | L97: 江西 | M97: 36.0000000000 | N97: 南昌市政公用投资控股（集团）有限责任公司 | O97: 深圳市城市交通规划设计研究/铁六院 | P97: 待定 | R97: 2025-12-31 | S97: CNY 0.000 | T97: 陈浩 | W97: 原规划的瑶湖隧道长度为5.5公里，重新规划后隧道长度缩短为3公里，因涉及到瑶湖岛上位规划未明确、瑶湖生态红线及建设资金的问题，市政府未下达项目近期实施的要求。 | X97: 持续关注项目后续进展 | Y97: 施工图设计阶段 | Z97: 原规划的瑶湖隧道长度为5.5公里，重新规划后隧道长度缩短为3公里，因涉及到瑶湖岛上位规划未明确、瑶湖生态红线及建设资金的问题，市政府未下达项目近期实施的要求。 | AA97: 一般信息（Ⅲ级） | AB97: 杨志胜 | AE97: 郭亚楠 | AF97: 跟进中 | AG97: 陈浩
A98: 46022 | B98: 2023-06-04 14:48:19 | C98: XM-2023060413955 | D98: 宜春东北绕城高速公路 | F98: 规划期内新建里程32公里，双向六车道，设计速度100公里/小时，预计投资45亿元。 | G98: 无 | H98: 公路-4 | I98: 特种装备事业部 | J98: 华东区域 | L98: 江西 | M98: 45.0000000000 | N98: 江西省交通投资集团有限责任公司项目建设管理公司 | O98: 江西省交通设计研究院有限责任公司 | Q98: 搅拌站-1-(2024-12-31); | R98: 2025-08-20 | S98: CNY 0.000 | T98: 陈浩 | W98: 核心问题：项目模式确定、项目建设资金来源、开工时间确定。 工作思路：依靠系统内单位运作。 关键点：无。 行动计划：拜访系统内单位，了解情况。 | X98: 持续关注项目后续进展，对接设计院 | Y98: 定测及初步设计阶段 | Z98: 拜访江西交通设计院,跟进项目进展情况， | AA98: 一般信息（Ⅲ级） | AB98: 杨志胜 | AE98: 郭亚楠 | AF98: 跟进中 | AG98: 陈浩
A99: 46022 | B99: 2023-06-04 15:05:17 | C99: XM-2023060413973 | D99: 福银高速江西段二通道 （九江至黄梅过江通道） | F99: 项目起点在九江市江洲镇（赣鄂界），终点在九江市新港镇，全长约11公里，是一座跨越长江的桥梁。 | G99: 无 | H99: 公路-4 | I99: 特种装备事业部 | J99: 华东区域 | L99: 江西 | M99: 85.0000000000 | N99: 九江市公路管理局 | O99: 长江航道勘察设计院（武汉）有限公司 | P99: 待定 | R99: 2025-12-31 | S99: CNY 0.000 | T99: 陈浩 | W99: 委托江西省交规院在做项目前期。 | X99: 持续关注项目后续进展 | Y99: 施工图设计阶段 | Z99: 拜访长江航道勘察设计院,跟进项目进展. | AA99: 一般信息（Ⅲ级） | AB99: 杨志胜 | AE99: 郭亚楠 | AF99: 跟进中 | AG99: 陈浩
A100: 46022 | B100: 2023-06-04 15:10:55 | C100: XM-2023060413980 | D100: 九江至小池过江通道 | F100: 初步推荐路线方案全长约90公里，项目估算总投资130亿元。 | G100: 初步推荐路线方案全长约90公里，项目估算总投资130亿元。 | H100: 公路-4 | I100: 交通工程装备事业部 | J100: 华东区域 | L100: 江西 | M100: 130.0000000000 | N100: 九江市公路管理局 | O100: 中铁上海院 | P100: 待定 | R100: 2025-12-31 | S100: CNY 0.000 | T100: 陈浩 | W100: 拜访设计院得知,该项目采用桥梁,不采用隧道. | X100: 拜访中铁上海院,跟进项目后续进展. | Y100: 施工图设计阶段 | Z100: 核心问题：项目是否采用隧道或者架桥. 工作思路：依靠系统内单位运作。 关键点：无。 行动计划：拜访系统内单位了解情况。 | AA100: 一般信息（Ⅲ级） | AB100: 杨志胜 | AE100: 郭亚楠 | AF100: 跟进中 | AG100: 陈浩
...

Sheet Sheet1
A1: 最后修改时间 | B1: (多项)
A3: 最后修改人 | B3: 计数项:项目名称
A4: 陈浩 | B4: 1
A5: 刘新峥 | B5: 10
A6: 沈腾飞 | B6: 9
A7: 唐作栋 | B7: 11
A8: 万赛 | B8: 1
A9: 杨志胜 | B9: 10
A10: 袁志凌 | B10: 3
A11: 赵宇瑄 | B11: 14
A12: 周斌 | B12: 14
A13: 总计 | B13: 73

Sheet Sheet3
A1: 责任人 | B1: 项目数量 | C1: 更新项目数量 | D1: 更新数量排名 | E1: 更新率 | F1: 更新率排名 | G1: 综合排名 （各占50%）
A2: 陈浩 | B2: 13 | C2: =VLOOKUP(A2,Sheet1!$A$3:$B$12,2,FALSE) -> 1 | D2: 8 | E2: =C2/B2 -> 0.076923077 | F2: 9 | G2: =D2*0.5+F2*0.5 -> 8.5
A3: 刘新峥 | B3: 11 | C3: 11 | D3: 3 | E3: =C3/B3 -> 1 | F3: 1 | G3: =D3*0.5+F3*0.5 -> 2
A4: 穆华清 | B4: 4 | C4: 0 | D4: 10 | E4: 0 | F4: 10 | G4: =D4*0.5+F4*0.5 -> 10
A5: 沈腾飞 | B5: 11 | C5: 10 | D5: 5 | E5: =C5/B5 -> 0.90909091 | F5: 4 | G5: =D5*0.5+F5*0.5 -> 4.5
A6: 唐作栋 | B6: 24 | C6: =VLOOKUP(A6,Sheet1!$A$3:$B$12,2,FALSE) -> 11 | D6: 3 | E6: =C6/B6 -> 0.45833333 | F6: 6 | G6: =D6*0.5+F6*0.5 -> 4.5
A7: 万赛 | B7: 7 | C7: =VLOOKUP(A7,Sheet1!$A$3:$B$12,2,FALSE) -> 1 | D7: 8 | E7: =C7/B7 -> 0.14285714 | F7: 8 | G7: =D7*0.5+F7*0.5 -> 8
A8: 杨志胜 | B8: 28 | C8: =VLOOKUP(A8,Sheet1!$A$3:$B$12,2,FALSE) -> 10 | D8: 5 | E8: =C8/B8 -> 0.35714286 | F8: 7 | G8: =D8*0.5+F8*0.5 -> 6
A9: 袁志凌 | B9: 3 | C9: =VLOOKUP(A9,Sheet1!$A$3:$B$12,2,FALSE) -> 3 | D9: 7 | E9: =C9/B9 -> 1 | F9: 1 | G9: =D9*0.5+F9*0.5 -> 4
A10: 赵宇瑄 | B10: 18 | C10: 15 | D10: 1 | E10: =C10/B10 -> 0.83333333 | F10: 5 | G10: =D10*0.5+F10*0.5 -> 3
A11: 周斌 | B11: 15 | C11: =VLOOKUP(A11,Sheet1!$A$3:$B$12,2,FALSE) -> 14 | D11: 2 | E11: =C11/B11 -> 0.93333333 | F11: 3 | G11: =D11*0.5+F11*0.5 -> 2.5
